{"descriptions":{"Joker":{"j_blueprint":{"text":["Salin kemampuan dari","{C:attention}Joker{} ke sebelah kanan"],"name":"Blueprint","unlock":["Menangi giliran"]},"j_drunkard":{"name":"Drunkard","text":["{C:red}+#1#{} discard","tiap babak"]},"j_stone":{"name":"Stone Joker","text":["Memberikan {C:chips}+#1#{} Chip untuk","setiap {C:attention}Stone Card","di {C:attention}deck lengkap kamu","{C:inactive}(Saat ini {C:chips}+#2#{C:inactive} Chip)"]},"j_golden":{"name":"Golden Joker","text":["Dapatkan {C:money}$#1#{} di","akhir babak"]},"j_joker":{"name":"Joker","text":["{C:red,s:1.1}+#1#{} Mult"]},"j_lucky_cat":{"name":"Lucky Card","text":["Joker ini mendapatkan {X:mult,C:white} X#1# {} Mult","setiap kali {C:attention}Lucky{} card","{C:green}sukses{} terpicu","{C:inactive}(Saat ini {X:mult,C:white} X#2# {C:inactive} Mult)"]},"j_baseball":{"name":"Baseball Card","text":["Setiap {C:green}Uncommon{} Joker","memberikan {X:mult,C:white} X#1# {} Mult"]},"j_bull":{"name":"Bull","text":["{C:chips}+#1#{} Chip untuk","setiap {C:money}$1{} yang dimiliki","{C:inactive}(Saat ini {C:chips}+#2#{C:inactive} Chip)"]},"j_greedy_joker":{"name":"Greedy Joker","text":["Kartu yang dimainkan dengan","{C:diamonds}#2#{} rupa memberikan","{C:mult}+#1#{} Mult saat menang"]},"j_diet_cola":{"name":"Diet Cola","text":["Jual kartu ini untuk","membuat sebuah","{C:attention}#1# gratis"]},"j_trading":{"name":"Trading Card","text":["Jika {C:attention}discard pertama{} dari babak","hanya memiliki {C:attention}1{} kartu, hancurkanlah","dan dapatkan {C:money}$#1#"]},"j_lusty_joker":{"name":"Lusty Joker","text":["Kartu yang dimainkan dengan","{C:hearts}#2#{} rupa memberikan","{C:mult}+#1#{} Mult saat menang"]},"j_flash":{"name":"Flash Card","text":["Joker ini mendapatkan {C:mult}+#1#{} Mult","tiap {C:attention}reroll{} di toko ","{C:inactive}(Saat ini {C:mult}+#2#{C:inactive} Mult)"]},"j_wrathful_joker":{"name":"Wrathful Joker","text":["Kartu yang dimainkan dengan","{C:spades}#2#{} rupa memberikan","{C:mult}+#1#{} Mult saat menang"]},"j_droll":{"name":"Droll Joker","text":["{C:red}+#1#{} Mult jika hand","yang dimainkan berisi","sebuah {C:attention}#2#"]},"j_gluttenous_joker":{"name":"Gluttonous Joker","text":["Kartu yang dimainkan dengan","{C:clubs}#2#{} rupa memberikan","{C:mult}+#1#{} Mult saat menang"]},"j_red_card":{"name":"Red Card","text":["Joker ini mendapatkan","{C:red}+#1#{} Mult jika ada","{C:attention}Booster Pack{} yang dilewati","{C:inactive}(Saat ini {C:red}+#2#{C:inactive} Mult)"]},"j_sly":{"name":"Sly Joker","text":["{C:chips}+#1#{} Chip jika hand","yang dimainkan berisi","sebuah {C:attention}#2#"]},"j_ancient":{"name":"Ancient Joker","text":["Setiap kartu yang dimainkan dengan","{V:1}#2#{} rupa memberikan","{X:mult,C:white} X#1# {} Mult saat menang,","{s:0.8}rupa berubah di akhir babak"]},"j_square":{"name":"Square Joker","text":["Joker ini mendapatkan {C:chips}+#2#{} Chip","jika hand yang dimainkan memiliki","tepat {C:attention}4{} kartu","{C:inactive}(Saat ini {C:chips}#1#{C:inactive} Chip)"]},"j_seance":{"name":"Séance","text":["Jika {C:attention}poker hand{} adalah sebuah","{C:attention}#1#{}, memunculkan sebuah","kartu {C:spectral}Spectral{} secara acak","{C:inactive}(Harus memiliki tempat)"]},"j_selzer":{"name":"Seltzer","text":["Memicu lagi semua","kartu yang dimainkan untuk","hand {C:attention}#1#{} berikutnya"]},"j_riff_raff":{"name":"Riff-raff","text":["Ketika {C:attention}Blind{} dipilih,","memunculkan {C:attention}#1# {C:blue}Common{C:attention} Joker","{C:inactive}(Harus memiliki tempat)"]},"j_crafty":{"name":"Crafty Joker","text":["{C:chips}+#1#{} Chip jika hand","yang dimainkan berisi","sebuah {C:attention}#2#"]},"j_vampire":{"name":"Vampire","text":["Joker ini mendapatkan {X:mult,C:white} X#1# {} Mult","tiap mencetak skor {C:attention}Peningkatan kartu{} yang dimainkan,","membuang {C:attention}Enhancement","{C:inactive}kartu (Saat ini {X:mult,C:white} X#2# {C:inactive} Mult)"]},"j_smiley":{"name":"Smiley Face","text":["Kartu {C:attention}wajah{} yang dimainkan","memberi {C:mult}+#1#{} Mult","saat menang"]},"j_shortcut":{"name":"Shortcut","text":["Memungkinkan {C:attention}Straight{} agar","dibuat dengan selisih {C:attention}1 peringkat","{C:inactive}(misalnya: {C:attention}10 8 6 5 3{C:inactive})"]},"j_campfire":{"name":"Campfire","text":["Joker ini memperoleh {X:mult,C:white}X#1#{} Mult","untuk setiap kartu {C:attention}yang dijual{}, mengatur ulang","ketika {C:attention}Boss Blind{} dikalahkan","{C:inactive}(Saat ini {X:mult,C:white} X#2# {C:inactive} Mult)"]},"j_hologram":{"name":"Hologram","text":["Joker ini mendapatkan {X:mult,C:white} X#1# {} Mult","setiap kali {C:attention}kartu yang dimainkan{}","ditambahkan ke deck kamu","{C:inactive}(Saat ini {X:mult,C:white} X#2# {C:inactive} Mult)"]},"j_stencil":{"name":"Joker Stencil","text":["{X:red,C:white} X1 {} Mult untuk setiap","slot {C:attention}Joker{} yang kosong","{s:0.8}termasuk Joker Stencil","{C:inactive}(Saat ini {X:red,C:white} X#1# {C:inactive})"]},"j_four_fingers":{"name":"Four Fingers","text":["Semua {C:attention}Flush{} dan","{C:attention}Straight{} bisa","dilakukan dengan {C:attention}4{} kartu"]},"j_baron":{"name":"Baron","text":["Setiap {C:attention}King{}","yang ada di hand","memberi {X:mult,C:white} X#1# {} Mult"]},"j_mr_bones":{"text":["Prevents Death","jika chip yang didapat","paling sedikit {C:attention}25%","dari chip yang diperlukan","{S:1.1,C:red,E:2}penghancuran diri{}"],"name":"Mr. Bones","unlock":["Kalah {C:attention,E:1}#1#{} giliran","{C:inactive}(#2#)"]},"j_cloud_9":{"name":"Cloud 9","text":["Dapatkan {C:money}$#1#{} untuk setiap","{C:attention}9{} di deck {C:attention}lengkap Anda","di akhir babak","{C:inactive}(Saat ini {C:money}$#2#{}{C:inactive})"]},"j_credit_card":{"name":"Credit Card","text":["Tingkatkan ke","{C:red}-$#1#{} berutang"]},"j_rocket":{"name":"Rocket","text":["Perolehan {C:money}$#1#{} di akhir babak","Payout meningkat sebesar {C:money}$#2#{}","jika {C:attention}Boss Blind{} dikalahkan"]},"j_acrobat":{"text":["{X:red,C:white} X#1# {} Mult di {C:attention}final","{C:attention}hand{} dari babak"],"name":"Acrobat","unlock":["Mainkan {C:attention,E:1}#1#{} hand","{C:inactive}(#2#)"]},"j_ceremonial":{"name":"Ceremonial Dagger","text":["Ketika {C:attention}Blind{} dipilih,","menghancurkan Joker ke sebelah kanan","dan secara permanen {C:attention}menggandakan","nilai jualnya ke Mult {C:red}ini","{C:inactive}(Saat ini {C:mult}+#1#{C:inactive} Mult)"]},"j_obelisk":{"name":"Obelisk","text":["Joker ini memperoleh {X:mult,C:white} X#1# {} Mult","per hand yang {C:attention}berturut-turut{} dimainkan","tanpa memainkan","{C:attention}poker hand","{C:inactive}yang paling sering dimainkan (Saat ini {X:mult,C:white} X#2# {C:inactive} Mult)"]},"j_banner":{"name":"Banner","text":["{C:chips}+#1#{} Chip untuk","setiap sisa","{C:attention}discard"]},"j_sock_and_buskin":{"text":["Picu lagi semua","face {C:attention}card{} yang dimainkan"],"name":"Sock and Buskin","unlock":["Mainkan total","{C:attention,E:1}#1#{} kartu wajah","{C:inactive}(#2#)"]},"j_mystic_summit":{"name":"Mystic Summit","text":["{C:mult}+#1#{} Mult ketika","{C:attention}#2#{} discard","sisa"]},"j_photograph":{"name":"Photograph","text":["Face card {C:attention}pertama","yang dimainkan memberi {X:mult,C:white} X#1# {} Mult","saat menang"]},"j_marble":{"name":"Marble Joker","text":["Menambah satu kartu {C:attention}Stone{}","ke deck saat","{C:attention}Blind{} dipilih"]},"j_troubadour":{"text":["{C:attention}+#1#{} ukuran hand,","{C:blue}-#2#{} hand setiap babak"],"name":"Troubadour","unlock":["Menangi {C:attention,E:1}#1#{} babak","berturut-turut dengan memainkan","1 hand saja"]},"j_loyalty_card":{"name":"Loyalty Card","text":["{X:red,C:white} X#1# {} Mult setiap","{C:attention}#2#{} hand yang dimainkan","{C:inactive}#3#"]},"j_erosion":{"name":"Erosion","text":["{C:red}+#1#{} Mult untuk setiap","kartu di bawah {C:attention}#3#{}","di deck lengkap Anda","{C:inactive}(Saat ini {C:red}+#2#{C:inactive} Mult)"]},"j_reserved_parking":{"name":"Reserved Parking","text":["Setiap {C:attention}kartu{} wajah","yang ada di hand memiliki","sebuah peluang {C:green}#2# dalam #3#{}","memberi {C:money}$#1#{}"]},"j_mail":{"name":"Mail-In Rebate","text":["Dapatkan {C:money}$#1#{} untuk setiap","{C:attention}#2#{} yang dibuang, peringkat","berubah setiap babak"]},"j_smeared":{"text":["{C:hearts}Hati{} dan {C:diamonds}Wajik","dianggap sebagai rupa yang sama,","{C:spades}Sekop{} dan {C:clubs}Keriting","dianggap sebagai rupa yang sama"],"name":"Smeared Joker","unlock":["Miliki setidaknya {C:attention}#1#","{E:1,C:attention}#2#{} di","ke deck Anda di"]},"j_to_the_moon":{"name":"To the Moon","text":["Dapatkan ekstra {C:money}$#1#{} dari","{C:attention}keuntungan{} untuk setiap {C:money}$5{} yang Anda","miliki di akhir babak"]},"j_misprint":{"name":"Misprint","text":[""]},"j_hallucination":{"name":"Hallucination","text":["{C:green}#1# dalam #2#{} peluang untuk membuat","sebuah kartu {C:tarot}Tarot{} ketika","{C:attention}Booster Pack{} dibuka","{C:inactive}(Harus memiliki tempat)"]},"j_fortune_teller":{"name":"Fortune Teller","text":["{C:red}+#1#{} Mult per","kartu {C:purple}Tarot{} dipakai","{C:inactive}(Saat ini {C:red}+#2#{C:inactive})"]},"j_juggler":{"name":"Juggler","text":["{C:attention}+#1#{} ukuran hand"]},"j_throwback":{"text":["{X:mult,C:white} X#1# {} Mult untuk setiap","{C:attention}Blind{} yang dilewati pada giliran ini","{C:inactive}(Saat ini {X:mult,C:white} X#2# {C:inactive} Mult)"],"name":"Throwback","unlock":["Lanjutkan giliran yang tersimpan","dari menu utama"]},"j_raised_fist":{"name":"Raised Fist","text":["Menambahkan {C:attention}dua kali{} peringkat","dari {C:attention}kartu{} dengan peringkat terendah","yang ada di hand untuk Mult"]},"j_hanging_chad":{"text":["Picu lagi {C:attention}kartu pertama{} yang dimainkan","yang digunakan dalam memenangkan","{C:attention}#1#{} kali tambahan"],"name":"Hanging Chad","unlock":["Kalahkan satu Boss Blind","dengan sebuah {E:1,C:attention}#1#"]},"j_chaos":{"name":"Chaos the Clown","text":["{C:attention}#1#{} Reroll {C:green}gratis","per toko"]},"j_rough_gem":{"text":["Kartu yang dimainkan dengan","rupa {C:diamonds}Wajik{} mendapatkan","{C:money}$#1#{} saat menang"],"name":"Rough Gem","unlock":["Miliki setidaknya {E:1,C:attention}#1#","kartu dengan {E:1,C:attention}#2#","rupa di deck Anda"]},"j_bloodstone":{"text":["{C:mult}+#1# dalam #2#{} peluang untuk","kartu yang dimainkan dengan","rupa {C:hearts}Hati{} memberikan","{X:mult,C:white} X#3# {} Mult saat menang,"],"name":"Bloodstone","unlock":["Miliki setidaknya {E:1,C:attention}#1#","kartu dengan {E:1,C:attention}#2#","rupa di deck Anda"]},"j_arrowhead":{"text":["Kartu yang dimainkan dengan","rupa {C:spades}Sekop{} memberikan","{C:chips}+#1#{} Chip saat menang"],"name":"Arrowhead","unlock":["Miliki setidaknya {E:1,C:attention}#1#","kartu dengan {E:1,C:attention}#2#","rupa di deck Anda"]},"j_steel_joker":{"name":"Steel Joker","text":["Memberikan {X:mult,C:white} X#1# {} Mult","untuk setiap {C:attention}Steel Card","di {C:attention}deck lengkap kamu","{C:inactive}(Saat ini {X:mult,C:white} X#2# {C:inactive} Mult)"]},"j_onyx_agate":{"text":["Kartu yang dimainkan dengan","rupa {C:clubs}Club{} memberikan","{C:mult}+#1#{} Mult saat menang"],"name":"Onyx Agate","unlock":["Miliki setidaknya {E:1,C:attention}#1#","kartu dengan {E:1,C:attention}#2#","rupa di deck Anda"]},"j_glass":{"text":["Joker ini mendapatkan {X:mult,C:white} X#1# {} Mult","untuk setiap {C:attention}Glass Card","yang dihancurkan","{C:inactive}(Saat ini {X:mult,C:white} X#2# {C:inactive} Mult)"],"name":"Glass Joker","unlock":["Miliki setidaknya {E:1,C:attention}#1#","{E:1,C:attention}#2#s{} di","deck Anda"]},"j_scary_face":{"name":"Scary Face","text":["Face {C:attention}card{} yang dimainkan","memberikan {C:chips}+#1#{} Chip","saat menang"]},"j_ring_master":{"text":["kartu {C:attention}Joker{}, {C:tarot}Tarot{}, {C:planet}Planet{}","dan {C:spectral}Spectral{} dapat","muncul berkali-kali"],"name":"Ring Master","unlock":["Reach Ante","level {E:1,C:attention}#1#"]},"j_abstract":{"name":"Abstract Joker","text":["{C:mult}+#1#{} Mult untuk","setiap kartu {C:attention}Joker{}","{C:inactive}(Saat ini {C:red}+#2#{C:inactive} Mult)"]},"j_flower_pot":{"text":["{X:mult,C:white} X#1# {} Mult jika poker","hand berisi","{C:diamonds}Diamond{} card, {C:clubs}Club{} card,","{C:hearts}Heart{} card, dan {C:spades}Spade{} card"],"name":"Flower Pot","unlock":["Reach Ante","level {E:1,C:attention}#1#"]},"j_hack":{"name":"Impostor","text":["Picu lagi","setiap dimainkan","{C:attention}2{}, {C:attention}3{}, {C:attention}4{}, atau {C:attention}5{}"]},"j_wee":{"text":["Joker ini memperoleh","{C:chips}+#2#{} Chip ketika setiap","{C:attention}2{} yang dimainkan menang","{C:inactive}(Saat ini {C:chips}+#1#{C:inactive} Chip)"],"name":"Wee Joker","unlock":["Menangi giliran dalam {E:1,C:attention}#1#","atau lebih sedikit babak"]},"j_pareidolia":{"name":"Pareidolia","text":["Semua kartu","dianggap","{C:attention}Kartu{} Wajah"]},"j_gros_michel":{"name":"Gros Michel","text":["{C:mult}+#1#{} Mult","{C:green}#2# dalam #3#{} peluang kartu","ini dihancurkan","di akhir babak"]},"j_oops":{"text":["Menggandakan semua {C:attention}yang terdaftar","{C:green,E:1,S:1.1}probabilitas","{C:inactive}(mis.: {C:green}1 in 3{C:inactive} -> {C:green}2 in 3{C:inactive})"],"name":"Oops! All 6s","unlock":["Dalam satu hand,","mendapat setidaknya","{E:1,C:attention}#1#{} chip"]},"j_even_steven":{"name":"Even Steven","text":["Kartu yang dimainkan dengan","peringkat {C:attention}genap{} memberikan","{C:mult}+#1#{} Mult saat menang","{C:inactive}(10, 8, 6, 4, 2)"]},"j_idol":{"text":["Setiap {C:attention}#2# yang dimainkan","dari {V:1}#3#{} memberikan","{X:mult,C:white} X#1# {} Mult saat menang","{s:0.8}Kartu berubah setiap babak"],"name":"The Idol","unlock":["Dalam satu hand,","mendapat setidaknya","{E:1,C:attention}#1#{} chip"]},"j_odd_todd":{"name":"Odd Todd","text":["Kartu yang dimainkan dengan","peringkat {C:attention}ganjil{} memberikan","{C:chips}+#1#{} Chip saat menang","{C:inactive}(A, 9, 7, 5, 3)"]},"j_scholar":{"name":"Scholar","text":["Setiap {C:attention}As{} yang dimainkan","memberi {C:chips}+#2#{} Chip","and {C:mult}+#1#{} Mult","saat menang"]},"j_matador":{"text":["Dapatkan {C:money}$#1#{} jika memainkan","hand memicu","kemampuan {C:attention}Boss Blind{}"],"name":"Matador","unlock":["Kalahkan satu Boss Blind","dalam {E:1,C:attention}1 hand{} tanpa","memakai discard apa pun"]},"j_hit_the_road":{"text":["Joker ini mendapatkan {X:mult,C:white} X#1# {} Mult","untuk setiap {C:attention}Jack{}","yang dibuang di babak ini","{C:inactive}(Saat ini {X:mult,C:white} X#2# {C:inactive} Mult)"],"name":"Hit the Road","unlock":["Buang {E:1,C:attention}5","{E:1,C:attention}Jack{} pada","saat bersamaan"]},"j_business":{"name":"Business Card","text":["Face {C:attention}card{} yang dimainkan memiliki","sebuah {C:green}#1# dalam #2#{} peluang untuk","memberikan {C:money}$2{} saat menang"]},"j_duo":{"text":["{X:mult,C:white} X#1# {} Mult jika hand","yang dimainkan berisi","sebuah {C:attention}#2#"],"name":"The Idol","unlock":["Menangi giliran","tanpa memainkan","sebuah {E:1,C:attention}#1#"]},"j_supernova":{"name":"Supernova","text":["Menambahkan berapa kali","{C:attention}poker hand{} telah","memainkan giliran ini ke Mult"]},"j_ride_the_bus":{"name":"Ride the Bus","text":["Joker ini memperoleh {C:mult}+#1#{} Mult","per {C:attention}hand{} yang dimainkan","berturut-turut tanpa","mencetak skor {C:attention}face{} card","{C:inactive}(Saat ini {C:mult}+#2#{C:inactive} Mult)"]},"j_space":{"name":"Space Joker","text":["{C:green}#1# dalam #2#{} peluang untuk","upgrade level dari","{C:attention}poker hand{} yang dimainkan"]},"j_egg":{"name":"Egg","text":["Memperoleh {C:money}$#1#{} dari","{C:attention}nilai jual{} di","akhir babak"]},"j_order":{"text":["{X:mult,C:white} X#1# {} Mult jika hand","yang dimainkan berisi","sebuah {C:attention}#2#"],"name":"The Order","unlock":["Menangi giliran","tanpa memainkan","sebuah {E:1,C:attention}#1#"]},"j_burglar":{"name":"Burglar","text":["Ketika {C:attention}Blind{} dipilih,","memperoleh {C:blue}+#1#{} Hand dan","{C:attention}kehilangan semua discard"]},"j_tribe":{"text":["{X:mult,C:white} X#1# {} Mult jika hand","yang dimainkan berisi","sebuah {C:attention}#2#"],"name":"The Tribe","unlock":["Menangi giliran","tanpa memainkan","sebuah {E:1,C:attention}#1#"]},"j_blackboard":{"name":"Blackboard","text":["{X:red,C:white} X#1# {} Mult jika semua","kartu yang ada di hand","adalah {C:spades}#2#{} atau {C:clubs}#3#{}"]},"j_stuntman":{"text":["{C:chips}+#1#{} Chip,","{C:attention}-#2#{} ukuran hand"],"name":"Stuntman","unlock":["Dalam satu hand,","dapatkan setidaknya","{E:1,C:attention}#1#{} chip"]},"j_runner":{"name":"Runner","text":["Memperoleh {C:chips}+#2#{} Chip","jika hand yang dimainkan","berisi sebuah {C:attention}Straight{}","{C:inactive}(Saat ini {C:chips}+#1#{C:inactive} Chip)"]},"j_invisible":{"text":["Setelah {C:attention}#1#{} babak,","jual kartu ini untuk","{C:attention}Duplicate{} Joker secara acak","{C:inactive}(Currently {C:attention}#2#{C:inactive}/#1#)"],"name":"Invisible Joker","unlock":["Menangi giliran tanpa","pernah memiliki lebih","dari {E:1,C:attention}4 Joker{}"]},"j_ice_cream":{"name":"Ice Cream","text":["{C:chips}+#1#{} Chip","{C:chips}-#2#{} Chip untuk","setiap hand yang dimainkan"]},"j_satellite":{"text":["Dapatkan {C:money}$#1#{} di akhir","babak per {C:planet}Planet unik","kartu yang dipakai pada giliran ini","{C:inactive}(Saat ini {C:money}$#2#{C:inactive})"],"name":"Satellite","unlock":["Miliki {E:1,C:money}$#1#","atau lebih"]},"j_splash":{"name":"Splash","text":["Setiap {C:attention}kartu yang dimainkan","dihitung dalam kemenangan"]},"j_shoot_the_moon":{"text":["Setiap {C:attention}Queen{}","yang ada di hand","memberikan {C:mult}+#1#{} Mult"],"name":"Shoot the Moon","unlock":["Mainkan setiap {E:1,C:attention}Hati","di deck Anda dalam","satu babak"]},"j_blue_joker":{"name":"Blue Joker","text":["{C:chips}+#1#{} Chip untuk setiap","kartu yang tersisa di {C:attention}deck","{C:inactive}(Saat ini {C:chips}+#2#{C:inactive} Chip)"]},"j_sixth_sense":{"name":"Sixth Sense","text":["Jika {C:attention}hand pertama{} dari babak ini adalah","sebuah {C:attention}6{}, menghancurkannya dan","memunculkan sebuah kartu {C:spectral}Spectral{}","{C:inactive}(Harus memiliki tempat)"]},"j_constellation":{"name":"Constellation","text":["Joker ini mendapatkan","{X:mult,C:white} X#1# {} Mult setiap kali","kartu {C:planet}Planet{} digunakan","{C:inactive}(Saat ini {X:mult,C:white} X#2# {C:inactive} Mult)"]},"j_hiker":{"name":"Hiker","text":["Setiap {C:attention}card{} yang dimainkan","secara permanen memperoleh","{C:chips}+#1#{} Chip saat menang"]},"j_faceless":{"name":"Faceless Joker","text":["Dapatkan {C:money}$#1#{} jika {C:attention}#2#{} atau","lebih banyak {C:attention}kartu wajah{}","yang dibuang","pada saat bersamaan"]},"j_astronomer":{"text":["Semua kartu {C:planet}Planet{} dan","{C:planet}Celestial Packs{} dalam","toko itu {C:attention}gratis"],"name":"Astronomer","unlock":["Temukan setiap","kartu{E:1,C:planet}Planet{}"]},"j_burnt":{"text":["Upgrade level dari","poker hand pertama {C:attention}yang dibuang","setiap babak"],"name":"Burnt Joker","unlock":["Jual hingga total","dari {E:1,C:attention}#1#{} kartu","{C:inactive}(#2#)"]},"j_superposition":{"name":"Superposition","text":["Memunculkan sebuah kartu {C:tarot}Tarot{} jika","poker hand berisi sebuah","{C:attention}As{} dan sebuah {C:attention}Straight{}","{C:inactive}(Harus memiliki tempat)"]},"j_bootstraps":{"text":["{C:mult}+#1#{} Mult untuk setiap","{C:money}$#2#{} yang kamu miliki","{C:inactive}(Saat ini {C:mult}+#3#{C:inactive} Mult)"],"name":"Bootstraps","unlock":["Miliki setidaknya {E:1,C:attention}#1#","Joker{C:dark_edition}Polychrome{}"]},"j_caino":{"text":["Joker ini mendapatkan {X:mult,C:white} X#1# {} Mult","jika {C:attention}face{} card","dihancurkan","{C:inactive}(Saat ini {X:mult,C:white} X#2# {C:inactive} Mult)"],"name":"Canio","unlock":["{E:1,s:1.3}?????"]},"j_cavendish":{"name":"Cavendish","text":["{X:mult,C:white} X#1# {} Mult","{C:green}#2# dalam #3#{} peluang kartu","ini dihancurkan","di akhir babak"]},"j_triboulet":{"text":["{C:attention}King{} dan","{C:attention}Queen{} yang dimainkan memberi","{X:mult,C:white} X#1# {} Mult saat menang,"],"name":"Triboulet","unlock":["{E:1,s:1.3}?????"]},"j_card_sharp":{"name":"Card Sharp","text":["{X:mult,C:white} X#1# {} Mult jika","{C:attention}poker hand{} yang telah","dimainkan pada babak ini"]},"j_chicot":{"text":["Nonaktifkan efek dari","setiap {C:attention}Boss Blind"],"name":"Chicot","unlock":["{E:1,s:1.3}?????"]},"j_perkeo":{"text":["Memunculkan sebuah salinan {C:dark_edition}Negatif{} dari","{C:attention}1{} kartu {C:attention}habis pakai{} secara acak","yang Anda miliki","di akhir dari {C:attention}toko"],"name":"Perkeo","unlock":["{E:1,s:1.3}?????"]},"j_zany":{"name":"Zany Joker","text":["{C:red}+#1#{} Mult jika hand","yang dimainkan berisi","sebuah {C:attention}#2#"]},"j_yorick":{"text":["Joker ini mendapatkan","{X:mult,C:white} X#1# {} Mult setiap {C:attention}#2#{C:inactive} [#3#]{}","kartu dibuang","{C:inactive}(Saat ini {X:mult,C:white} X#4# {C:inactive} Mult)"],"name":"Yorick","unlock":["{E:1,s:1.3}?????"]},"j_wily":{"name":"Wily Joker","text":["{C:chips}+#1#{} Chip jika hand","yang dimainkan berisi","sebuah {C:attention}#2#"]},"j_walkie_talkie":{"name":"Walkie Talkie","text":["Setiap {C:attention}10{} atau {C:attention}4 yang dimainkan","memberi {C:chips}+#1#{} Chip dan","{C:mult}+#2#{} Mult saat menang"]},"j_vagabond":{"name":"Vagabond","text":["Buat sebuah kartu {C:purple}Tarot{}","jika hand dimainkan","dengan {C:money}$#1#{} atau kurang"]},"j_turtle_bean":{"name":"Turtle Bean","text":["{C:attention}+#1#{} ukuran hand,","berkurang sebanyak","{C:red}#2#{} setiap babak"]},"j_trousers":{"name":"Spare Trousers","text":["Joker ini mendapatkan {C:mult}+#1#{} Mult","jika hand yang dimainkan berisi","satu {C:attention}#2#","{C:inactive}(Saat ini {C:red}+#3#{C:inactive} Mult)"]},"j_trio":{"text":["{X:mult,C:white} X#1# {} Mult jika hand","yang dimainkan berisi","sebuah {C:attention}#2#"],"name":"The Trio","unlock":["Menangi giliran","tanpa memainkan","sebuah {E:1,C:attention}#1#"]},"j_todo_list":{"name":"To Do List","text":["Dapatkan {C:money}$#1#{} jika {C:attention}poker hand{}","merupakan {C:attention}#2#{},","poker hand berubah","di akhir babak"]},"j_ticket":{"text":["Kartu {C:attention}Gold{} yang dimainkan","mendapatkan {C:money}$#1#{} saat menang"],"name":"Golden Ticket","unlock":["Ketika 5 kartu hand","yang hanya memiliki","kartu {C:attention,E:1}Gold{}"]},"j_swashbuckler":{"text":["Menambah nilai jual","semua","{C:attention}Joker{} lain yang dimiliki ke Mult","{C:inactive}(Saat ini {C:mult}+#1#{C:inactive} Mult)"],"name":"Swashbuckler","unlock":["Jual hingga total","Kartu {C:attention,E:1}#1#{} Joker","{C:inactive}(#2#)"]},"j_green_joker":{"name":"Green Joker","text":["{C:mult}+#1#{} Mult per hand yang dimainkan","{C:mult}-#2#{} Mult per discard","{C:inactive}(Saat ini {C:mult}+#3#{C:inactive} Mult)"]},"j_dusk":{"name":"Dusk","text":["Picu lagi semua kartu","kartu di {C:attention}final","{C:attention}hand{} dari babak"]},"j_fibonacci":{"name":"Fibonacci","text":["Setiap {C:attention}As{} yang dimainkan,","{C:attention}2{}, {C:attention}3{}, {C:attention}5{}, atau {C:attention}8{} memberikan","{C:mult}+#1#{} Mult saat menang"]},"j_delayed_grat":{"name":"Delayed Gratification","text":["Dapatkan {C:money}$#1#{} per {C:attention}discard{} jika","tidak ada discard yang dipakai","pada akhir babak"]},"j_castle":{"name":"Castle","text":["Joker ini memperoleh {C:chips}+#1#{} Chip","setiap kartu {V:1}#2#{} yang dibuang,","rupa berubah setiap babak","{C:inactive}(Saat ini {C:chips}+#3#{C:inactive} Chip)"]},"j_cartomancer":{"text":["Memunculkan sebuah kartu {C:tarot}Tarot{}","ketika {C:attention}Blind{} dipilih","{C:inactive}(Harus memiliki tempat)"],"name":"Cartomancer","unlock":["Temukan setiap","kartu {E:1,C:tarot}Tarot{}"]},"j_8_ball":{"name":"8 Ball","text":["{C:green}#1# di #2#{} peluang untuk setiap","8 {C:attention}yang dimainkan{} untuk membuat kartu","{C:tarot}Tarot{} saat menang","{C:inactive}(Harus memiliki tempat)"]},"j_certificate":{"text":["Saat babak dimulai,","tambahkan sebuah {C:attention}acak memainkan","{C:attention}kartu{} dengan acak","{C:attention}seal{} ke hand Anda"],"name":"Certificate","unlock":["Have a Gold","memainkan kartu dengan","sebuah {C:attention,E:1}Gold Seal"]},"j_brainstorm":{"text":["Menyalin kemampuan","dari {C:attention}Joker paling kiri"],"name":"Brainstorm","unlock":["Buang sebuah","{E:1,C:attention}Royal Flush"]},"j_madness":{"name":"Madness","text":["Jika {C:attention}Small Blind{} atau {C:attention}Big Blind{}","dipilih, akan didapat {X:mult,C:white} X#1# {} Mult","dan {C:attention}menghancurkan{} Joker acak","{C:inactive}(Saat ini {X:mult,C:white} X#2# {C:inactive} Mult)"]},"j_gift":{"name":"Gift Card","text":["Menambah {C:money}$#1#{} dari {C:attention}nilai jual","ke setiap kartu {C:attention}Joker{} dan","{C:attention}Habis Pakai{} di","akhir babak"]},"j_merry_andy":{"text":["{C:red}+#1#{} membuang","setiap babak,","{C:red}#2#{} ukuran hand"],"name":"Merry Andy","unlock":["Menangi giliran dalam {E:1,C:attention}#1#","atau lebih sedikit babak"]},"j_luchador":{"name":"Luchador","text":["Jual kartu ini untuk","menonaktifkan","{C:attention}Boss Blind{} saat ini"]},"j_mime":{"name":"Mime","text":["Picu lagi semua","kartu yang {C:attention}disimpan dalam","kemampuan {C:attention}hand{}"]},"j_midas_mask":{"name":"Midas Mask","text":["Semua kartu {C:attention}wajah{} yang dimainkan","menjadi {C:attention}kartu{} Gold","jika mendapatkan skor"]},"j_half":{"name":"Half Joker","text":["{C:red}+#1#{} Mult jika hand","yang dimainkan berisi","{C:attention}#2#{} atau kartu lebih sedikit"]},"j_mad":{"name":"Mad Joker","text":["{C:red}+#1#{} Mult jika hand","yang dimainkan berisi","sebuah {C:attention}#2#"]},"j_devious":{"name":"Devious Joker","text":["{C:chips}+#1#{} Chip jika hand","yang dimainkan berisi","sebuah {C:attention}#2#"]},"j_clever":{"name":"Clever Joker","text":["{C:chips}+#1#{} Chip jika hand","yang dimainkan berisi","sebuah {C:attention}#2#"]},"j_crazy":{"name":"Crazy Joker","text":["{C:red}+#1#{} Mult jika hand","yang dimainkan berisi","sebuah {C:attention}#2#"]},"j_jolly":{"name":"Jolly Joker","text":["{C:red}+#1#{} Mult jika hand","yang dimainkan berisi","sebuah {C:attention}#2#"]},"j_drivers_license":{"text":["{X:mult,C:white} X#1# {} Mult jika Anda","memiliki setidaknya {C:attention}16","kartu enhanced","{C:inactive}(Saat ini {C:attention}#2#{C:inactive})"],"name":"Driver's License","unlock":["Tingkatkan {E:1,C:attention}#1#{} kartu","di deck Anda"]},"j_popcorn":{"name":"Popcorn","text":["{C:mult}+#1#{} Mult","{C:mult}-#2#{} Mult setiap","babak yang dimainkan"]},"j_dna":{"name":"DNA","text":["Jika {C:attention}hand pertama{} dari babak","hanya memiliki {C:attention}1{} kartu, tambahkan","salinan permanen ke deck","dan ambil ke {C:attention}hand"]},"j_family":{"text":["{X:mult,C:white} X#1# {} Mult jika hand","yang dimainkan berisi","sebuah {C:attention}#2#"],"name":"The Family","unlock":["Menangi giliran","tanpa memainkan","sebuah {E:1,C:attention}#1#"]},"j_ramen":{"name":"Ramen","text":["{X:mult,C:white} X#1# {} Mult,","kehilangan {X:mult,C:white} X#2# {} Mult","setiap {C:attention}kartu{} yang dibuang"]},"j_seeing_double":{"text":["{X:mult,C:white} X#1# {} Mult jika hand","yang dimainkan memiliki sebuah kemenangan","kartu{C:clubs}Keriting{} dan kartu","yang menang dari rupa {C:attention}lainnya"],"name":"Seeing Double","unlock":["Mainkan sebuah hand","yang memiliki","{E:1,C:attention}#1#"]}},"Tag":{"tag_uncommon":{"name":"Uncommon Tag","text":["Shop memiliki","{C:green}Uncommon Joker gratis"]},"tag_voucher":{"name":"Voucher Tag","text":["Menambah satu {C:voucher}Voucher","ke babak berikutnya"]},"tag_d_six":{"name":"D6 Tag","text":["Reroll di babak berikutnya","mulai dari {C:money}$0"]},"tag_boss":{"name":"Boss Tag","text":["Reroll","{C:attention}Boss Blind"]},"tag_top_up":{"name":"Top-up Tag","text":["Memunculkan hingga {C:attention}#1#","{C:blue}Common{} Joker","{C:inactive}(Harus memiliki tempat)"]},"tag_rare":{"name":"Rare Tag","text":["Shop memiliki","{C:red}Rare Joker gratis"]},"tag_skip":{"name":"Speed Tag","text":["Memberikan {C:money}$#1#{} per","Blind yang dilewati pada giliran ini","{C:inactive}(Akan memberi {C:money}$#2#{C:inactive})"]},"tag_charm":{"name":"Charm Tag","text":["Memberikan gratis","{C:tarot}Mega Arcana Pack"]},"tag_meteor":{"name":"Meteor Tag","text":["Memberikan gratis","{C:planet}Mega Celestial Pack"]},"tag_negative":{"name":"Tag Negatif","text":["Joker","shop edisi dasar selanjutnya gratis dan","menjadi {C:dark_edition}Negatif"]},"tag_buffoon":{"name":"Buffoon Tag","text":["Memberikan gratis","{C:attention}Buffoon Pack"]},"tag_economy":{"name":"Economy Tag","text":["Menggandakan uang Anda","{C:inactive}(Maks {C:money}$#1#{C:inactive})"]},"tag_handy":{"name":"Handy Tag","text":["Memberikan {C:money}$#1#{} per hand","{C:blue}yang dimainkan{} pada giliran ini","{C:inactive}(Akan memberi {C:money}$#2#{C:inactive})"]},"tag_foil":{"name":"Foil Tag","text":["Joker","shop edisi dasar selanjutnya gratis dan","menjadi {C:dark_edition}Foil"]},"tag_garbage":{"name":"Garbage Tag","text":["Memberikan {C:money}$#1#{} per discard","{C:red}yang tidak dipakai{} pada giliran ini","{C:inactive}(Akan memberi {C:money}$#2#{C:inactive})"]},"tag_ethereal":{"name":"Ethereal Tag","text":["Memberikan gratis","{C:planet}Spectral Pack"]},"tag_coupon":{"name":"Coupon Tag","text":["Kartu perdana dan","paket booster di toko","toko itu gratis"]},"tag_standard":{"name":"Standard Tag","text":["Memberikan gratis","{C:attention}Mega Standard Pack"]},"tag_polychrome":{"name":"Polychrome Tag","text":["Joker","shop edisi dasar selanjutnya gratis dan","menjadi {C:dark_edition}Polychrome"]},"tag_double":{"name":"Double Tag","text":["Memberikan sebuah salinan","{C:attention}Tag{} pilihan berikutnya","{s:0.8}tidak termasuk {s:0.8,C:attention}Double Tag"]},"tag_orbital":{"name":"Orbital Tag","text":["Upgrade {C:attention}#1#","sebanyak {C:attention}#2# level"]},"tag_holo":{"name":"Holographic Tag","text":["Joker","shop edisi dasar selanjutnya gratis dan","menjadi {C:dark_edition}Holographic"]},"tag_juggle":{"name":"Juggle Tag","text":["{C:attention}+#1#{} ukuran hand","babak berikutnya"]},"tag_investment":{"name":"Investment Tag","text":["Setelah mengalahkan","si Boss Blind,","dapatkan {C:money}$#1#"]}},"Other":{"p_arcana_mega":{"name":"Mega Arcana Pack","text":["Pilih sampai {C:attention}#1#{} dari","{C:attention}#2#{C:tarot} kartu{} Tarot untuk","segera dipakai"]},"card_chips":{"text":["{C:chips}+#1#{} chip"]},"card_extra_chips":{"text":["{C:chips}+#1#{} chip ekstra"]},"p_buffoon_jumbo":{"name":"Jumbo Buffoon Pack","text":["Pilih sampai {C:attention}#1#{} dari","{C:attention}#2#{C:joker} kartu{} Joker"]},"challenge_locked":{"name":"Dikunci","text":["Menangi giliran dengan setidaknya","#1# deck lain untuk membuka","Mode tantangan","{C:attention,s:2}#2#/#1#"]},"p_buffoon_mega":{"name":"Mega Buffoon Pack","text":["Pilih sampai {C:attention}#1#{} dari","{C:attention}#2#{C:joker} kartu{} Joker"]},"p_buffoon_normal":{"name":"Buffoon Pack","text":["Pilih sampai {C:attention}#1#{} dari","{C:attention}#2#{C:joker} kartu{} Joker"]},"debuffed_default":{"name":"Di-debuff","text":["Semua kemampuan","dinonaktifkan"]},"debuffed_playing_card":{"name":"Di-debuff","text":["Tidak mendapat chip","dan semua kemampuan","dinonaktifkan"]},"p_celestial_mega":{"name":"Mega Celestial Pack","text":["Pilih sampai {C:attention}#1#{} dari","{C:attention}#2#{C:planet} kartu{} Planet untuk","segera dipakai"]},"undiscovered_joker":{"name":"Belum Ditemukan","text":["Beli atau pakai","kartu ini dalam sebuah","giliran yang tidak diunggulkan untuk","mempelajari apa fungsinya"]},"p_celestial_normal":{"name":"Celestial Pack","text":["Pilih sampai {C:attention}#1#{} dari","{C:attention}#2#{C:planet} kartu{} Planet untuk","segera dipakai"]},"p_spectral_jumbo":{"name":"Jumbo Spectral Pack","text":["Pilih sampai {C:attention}#1#{} dari","{C:attention}#2#{C:spectral} kartu{} Spectral untuk","segera dipakai"]},"wip_locked":{"name":"Dikunci","text":["Pekerjaan sedang","berlangsung"]},"p_spectral_mega":{"name":"Mega Spectral Pack","text":["Pilih sampai {C:attention}#1#{} dari","{C:attention}#2#{C:spectral} kartu{} Spectral untuk","segera dipakai"]},"deck_locked_win":{"name":"Dikunci","text":["Menangi giliran dengan","{C:attention}#1#{}","pada kesulitan apa pun"]},"p_spectral_normal":{"name":"Spectral Pack","text":["Pilih sampai {C:attention}#1#{} dari","{C:attention}#2#{C:spectral} kartu{} Spectral untuk","segera dipakai"]},"white_sticker":{"name":"White Sticker","text":["Dipakai Joker ini","untuk menang di kesulitan {C:attention}White","{C:attention}Stake{}"]},"p_standard_jumbo":{"name":"Jumbo Standard Pack","text":["Pilih sampai {C:attention}#1#{} dari","{C:attention}#2#{C:attention} kartu{} Permainan untuk","ditambahkan ke deck Anda"]},"demo_locked":{"name":"Dikunci","text":["Tidak tersedia","dalam demo ini"]},"undiscovered_voucher":{"name":"Belum Ditemukan","text":["Tukarkan voucher","ini dalam sebuah","giliran yang tidak diunggulkan untuk","mempelajari apa fungsinya"]},"undiscovered_tarot":{"name":"Belum Ditemukan","text":["Beli atau pakai","kartu ini dalam sebuah","giliran yang tidak diunggulkan untuk","mempelajari apa fungsinya"]},"demo_shop_locked":{"name":"Dikunci","text":["Kartu dari {C:attention}koleksi","pribadi Jimbo,","tersedia di versi","lengkapnya {E:1,C:red}Balatro"]},"undiscovered_tag":{"name":"Belum Ditemukan","text":["Pakai tag ini saat","giliran yang tidak diunggulkan untuk","mempelajari apa fungsinya"]},"p_standard_normal":{"name":"Standard Pack","text":["Pilih sampai {C:attention}#1#{} dari","{C:attention}#2#{C:attention} kartu{} Permainan untuk","ditambahkan ke deck Anda"]},"undiscovered_spectral":{"name":"Belum Ditemukan","text":["Beli atau pakai","kartu ini dalam sebuah","giliran yang tidak diunggulkan untuk","mempelajari apa fungsinya"]},"undiscovered_planet":{"name":"Belum Ditemukan","text":["Beli atau pakai","kartu ini dalam sebuah","giliran yang tidak diunggulkan untuk","mempelajari apa fungsinya"]},"eternal":{"name":"Eternal","text":["Tidak bisa dijual","atau dihancurkan"]},"undiscovered_edition":{"name":"Belum Ditemukan","text":["Temukan edisi ini","saat giliran yang tidak diunggulkan untuk","mempelajari apa fungsinya"]},"undiscovered_booster":{"name":"Belum Ditemukan","text":["Buka paket ini","saat giliran yang tidak diunggulkan untuk","mempelajari apa fungsinya"]},"rental":{"name":"Rental","text":["Kehilangan {C:money}$#1#{} pada","akhir babak"]},"gold_seal":{"name":"Gold Seal","text":["Dapatkan {C:money}$3{} saat kartu","ini dimainkan","dan menang"]},"pinned_left":{"name":"Disematkan","text":["Joker ini tetap","disematkan ke","posisi paling kiri"]},"p_arcana_normal":{"name":"Arcana Pack","text":["Pilih sampai {C:attention}#1#{} dari","{C:attention}#2#{C:tarot} kartu{} Tarot untuk","segera dipakai"]},"red_sticker":{"name":"Red Sticker","text":["Dipakai Joker ini","untuk menang di kesulitan {C:attention}Red","{C:attention}Stake{}"]},"red_seal":{"name":"Red Seal","text":["Picu lagi kartu","ini {C:attention}1{} kali"]},"gold_sticker":{"name":"Gold Sticker","text":["Dipakai Joker ini","untuk menang di kesulitan {C:attention}Gold","{C:attention}Stake{}"]},"purple_sticker":{"name":"Purple Sticker","text":["Dipakai Joker ini","untuk menang di kesulitan {C:attention}Purple","{C:attention}Stake{}"]},"purple_seal":{"name":"Purple Seal","text":["Membuat sebuah kartu {C:tarot}Tarot{}","ketika {C:attention}dibuang","{C:inactive}(Harus memiliki tempat)"]},"green_sticker":{"name":"Green Sticker","text":["Dipakai Joker ini","untuk menang di kesulitan {C:attention}Green","{C:attention}Stake{}"]},"p_standard_mega":{"name":"Mega Standard Pack","text":["Pilih sampai {C:attention}#1#{} dari","{C:attention}#2#{C:attention} kartu{} Permainan untuk","ditambahkan ke deck Anda"]},"perishable":{"name":"Perishable","text":["Di-debuff setelah","{C:attention}#1#{} babak","{C:inactive}({C:attention}#2#{C:inactive} tersisa)"]},"joker_locked_legendary":{"name":"Dikunci","text":["Temukan Joker ini","dari kartu {C:spectral}Soul{}"]},"black_sticker":{"name":"Black Sticker","text":["Dipakai Joker ini","untuk menang di kesulitan {C:attention}Black","{C:attention}Stake{}"]},"playing_card":{"text":[" {C:light_black}#1# dari {V:1}#2# "]},"locked":{"name":"Dikunci","text":[]},"orange_sticker":{"name":"Orange Sticker","text":["Dipakai Joker ini","untuk menang di kesulitan {C:attention}Orange","{C:attention}Stake{}"]},"p_celestial_jumbo":{"name":"Jumbo Celestial Pack","text":["Pilih sampai {C:attention}#1#{} dari","{C:attention}#2#{C:planet} kartu{} Planet untuk","segera dipakai"]},"blue_seal":{"name":"Blue Seal","text":["Membuat kartu {C:planet}Planet{}","untuk {C:attention}poker hand{}","terakhir yang dimainkan pada babak tersebut jika {C:attention}ada{} di hand","{C:inactive}(Harus memiliki tempat)"]},"p_arcana_jumbo":{"name":"Jumbo Arcana Pack","text":["Pilih sampai {C:attention}#1#{} dari","{C:attention}#2#{C:tarot} kartu{} Tarot untuk","segera dipakai"]},"deck_locked_stake":{"name":"Dikunci","text":["Menangi giliran dengan","deck apa pun setidaknya pada","kesulitan {V:1}#1#{}"]},"deck_locked_discover":{"name":"Dikunci","text":["Temukan setidaknya","{C:attention}#1#{} item dari","koleksi Anda"]},"remove_negative":{"name":"Negatif","text":["{C:inactive,s:0.9}(Hapus {C:dark_edition,s:0.9}Negatif{C:inactive,s:0.9} dari salinan)"]},"blue_sticker":{"name":"Blue Sticker","text":["Dipakai Joker ini","untuk menang di kesulitan {C:attention}Blue","{C:attention}Stake{}"]}},"Blind":{"bl_final_leaf":{"name":"Verdant Leaf","text":["Semua kartu di-debuff","hingga 1 Joker dijual"]},"bl_wheel":{"name":"The Wheel","text":[" dalam 7 kartu menarik","ditarik menghadap ke bawah"]},"bl_final_vessel":{"name":"Violet Vessel","text":["Blind sangat besar"]},"bl_window":{"name":"The Window","text":["Semua kartu Hati","di-debuff"]},"bl_arm":{"name":"The Arm","text":["Turunkan level","poker hand yang dimainkan"]},"bl_wall":{"name":"The Wall","text":["Blind ekstra besar"]},"bl_water":{"name":"The Water","text":["Mulai dengan","0 discard"]},"bl_psychic":{"name":"The Psychic","text":["Harus memainkan 5 kartu"]},"bl_house":{"name":"The House","text":["Hand pertama adalah","ditarik menghadap ke bawah"]},"bl_tooth":{"name":"The Tooth","text":["Kehilangan $1 per","kartu yang dimainkan"]},"bl_small":{"name":"Small Blind","text":[]},"bl_goad":{"name":"The Goad","text":["Semua kartu Sekop","di-debuff"]},"bl_serpent":{"name":"The Serpent","text":["Setelah Bermain atau Membuang,","harus menarik 3 kartu"]},"bl_ox":{"name":"The Ox","text":["Memainkan sebuah #1#","membuat uang hingga $0"]},"bl_final_bell":{"name":"Cerulean Bell","text":["Memaksakan 1 kartu pada","kartu yang selalu dipilih"]},"bl_plant":{"name":"The Plant","text":["Semua kartu wajah","di-debuff"]},"bl_pillar":{"name":"The Pillar","text":["Kartu yang dimainkan sebelumnya","sebelum Ante ini di-debuff"]},"bl_eye":{"name":"The Eye","text":["Tidak ada jenis","repeat hand pada babak ini"]},"bl_needle":{"name":"The Needle","text":["Mainkan 1 hand saja"]},"bl_hook":{"name":"The Hook","text":["Membuang 2 kartu secara","acak per hand yang dimainkan"]},"bl_final_heart":{"name":"Crimson Heart","text":["Sebuah Joker secara acak","dinonaktifkan setiap hand"]},"bl_mark":{"name":"The Mark","text":["Semua kartu wajah","ditarik menghadap ke bawah"]},"bl_mouth":{"name":"The Mouth","text":["Mainkan 1 jenis hand","saja pada babak ini"]},"bl_final_acorn":{"name":"Amber Acorn","text":["Balik dan kocok","semua kartu Joker"]},"bl_club":{"name":"The Club","text":["Semua kartu Keriting","di-debuff"]},"bl_fish":{"name":"The Fish","text":["Kartu yang ditarik menghadap ke bawah","setelah setiap hand dimainkan"]},"bl_big":{"name":"Big Blind","text":[]},"bl_flint":{"name":"The Flint","text":["Base Chip dan","Mult dibagi dua"]},"bl_head":{"name":"The Head","text":["Semua kartu Hati","di-debuff"]},"bl_manacle":{"name":"The Manacle","text":["-1 Ukuran Hand"]}},"Enhanced":{"m_lucky":{"name":"Lucky Card","text":["{C:green}#1# dalam #3#{} peluang","untuk {C:mult}+#2#{} Mult","{C:green}#1# dalam #5#{} peluang","untuk memenangi {C:money}$#4#"]},"m_gold":{"name":"Gold Card","text":["{C:money}$#1#{} jika ini","ini ada di hand","di akhir babak"]},"m_glass":{"name":"Glass Card","text":["{X:mult,C:white} X#1# {} Mult","{C:green}#2# dalam #3#{} peluang untuk","menghancurkan kartu"]},"m_wild":{"name":"Wild Card","text":["Bisa dipakai","sebagai rupa apa pun"]},"m_stone":{"name":"Stone Card","text":["{C:chips}+#1#{} Chip","tanpa peringkat atau rupa"]},"m_steel":{"name":"Steel Card","text":["{X:mult,C:white} X#1# {} Mult","sedangkan kartu ini","tetap di hand"]},"m_bonus":{"name":"Bonus Card","text":[]},"m_mult":{"name":"Mult Card","text":["{C:mult}+#1#{} Mult"]}},"Tarot":{"c_death":{"name":"Death","text":["Pilih {C:attention}#1#{} kartu,","mengubah kartu {C:attention}kiri{}","menjadi kartu {C:attention}kanan{}","{C:inactive}(Seret untuk mengatur kembali)"]},"c_high_priestess":{"name":"The High Priestess","text":["Memunculkan hingga {C:attention}#1#","kartu {C:planet}Planet{} secara acak","{C:inactive}(Harus memiliki tempat)"]},"c_empress":{"name":"The Empress","text":["Meningkatkan {C:attention}#1#","kartu pilihan hingga","{C:attention}#2#s"]},"c_emperor":{"name":"The Emperor","text":["Memunculkan hingga {C:attention}#1#","kartu {C:tarot}Tarot{} secara acak","{C:inactive}(Harus memiliki tempat)"]},"c_tower":{"name":"The Tower","text":["Meningkatkan {C:attention}#1#{} kartu","pilihan ke dalam","{C:attention}#2#"]},"c_heirophant":{"name":"The Hierophant","text":["Meningkatkan {C:attention}#1#","kartu pilihan hingga","{C:attention}#2#s"]},"c_star":{"name":"The Star","text":["Mengubah hingga","{C:attention}#1#{} kartu pilihan","menjadi {V:1}#2#{}"]},"c_lovers":{"name":"The Lovers","text":["Meningkatkan {C:attention}#1#{} kartu","pilihan ke dalam","{C:attention}#2#"]},"c_chariot":{"name":"The Chariot","text":["Meningkatkan {C:attention}#1#{} kartu","pilihan ke dalam","{C:attention}#2#"]},"c_justice":{"name":"Justice","text":["Meningkatkan {C:attention}#1#{} kartu","pilihan ke dalam","{C:attention}#2#"]},"c_world":{"name":"The World","text":["Mengubah hingga","{C:attention}#1#{} kartu pilihan","menjadi {V:1}#2#{}"]},"c_hermit":{"name":"The Hermit","text":["Menggandakan uang","{C:inactive}(Maks {C:money}$#1#{C:inactive})"]},"c_sun":{"name":"The Sun","text":["Mengubah hingga","{C:attention}#1#{} kartu pilihan","menjadi {V:1}#2#{}"]},"c_temperance":{"name":"Temperance","text":["Memberikan total nilai","jual semua","Joker saat ini {C:inactive}(Maks {C:money}$#1#{C:inactive})","{C:inactive}(Saat ini {C:money}$#2#{C:inactive})"]},"c_wheel_of_fortune":{"name":"The Wheel of Fortune","text":["{C:green}#1# dalam #2#{} peluang untuk menambah","edisi {C:dark_edition}Foil{}, {C:dark_edition}Holographic{}, dan","{C:dark_edition}Polychrome{}","menghancurkan sebuah {C:attention}Joker secara acak"]},"c_fool":{"name":"The Fool","text":["Memunculkan","kartu {C:tarot}Tarot{} atau {C:planet} Planet{}","dipakai pada giliran ini","{s:0.8,C:tarot}The Fool{s:0.8} tidak termasuk"]},"c_strength":{"name":"Strength","text":["Menaikkan peringkat","hingga {C:attention}#1#{} kartu","pilihan sebanyak {C:attention}1"]},"c_hanged_man":{"name":"The Hanged Man","text":["Menghancurkan hingga","{C:attention}#1#{} kartu pilihan"]},"c_judgement":{"name":"Judgement","text":["Memunculkan secara acak","kartu {C:attention}Joker{}","{C:inactive}(Harus memiliki tempat)"]},"c_magician":{"name":"The Magician","text":["Meningkatkan {C:attention}#1#{}","kartu pilihan hingga","{C:attention}#2#"]},"c_devil":{"name":"The Devil","text":["Meningkatkan {C:attention}#1#{} kartu","pilihan ke dalam","{C:attention}#2#"]},"c_moon":{"name":"The Moon","text":["Mengubah hingga","{C:attention}#1#{} kartu pilihan","menjadi {V:1}#2#{}"]}},"Voucher":{"v_overstock_plus":{"text":["{C:attention}+1{} slot kartu","tersedia di toko"],"name":"Overstock Plus","unlock":["Belanjakan total","{C:money}$#1#{} di toko","{C:inactive}($#2#)"]},"v_money_tree":{"text":["Naikkan batas","bunga yang diperoleh di","setiap babak menjadi {C:money}$#1#{}"],"name":"Money Tree","unlock":["Maksimalkan keuntungan","pendapatan per babak selama","{C:attention}#1#{} babak berturut-turut","{C:inactive}(#2#)"]},"v_telescope":{"name":"Telescope","text":["{C:attention}Celestial Pack{} selalu","berisi kartu {C:planet}Planet{}","untuk","poker hand {C:attention}yang paling banyak dimainkan"]},"v_antimatter":{"text":["{C:dark_edition}+1{} Joker Slot"],"name":"Antimatter","unlock":["Tukarkan {C:voucher}Blank{}","total {C:attention}#1#{} kali","{C:inactive}(#2#)"]},"v_clearance_sale":{"name":"Clearance Sale","text":["Semua kartu dan paket di","toko itu diskon {C:attention}#1#%{}"]},"v_tarot_tycoon":{"text":["Kartu {C:tarot}Tarot{} muncul","{C:attention}#1#X{} lebih sering","di toko"],"name":"Tarot Tycoon","unlock":["Beli total","kartu {C:attention}#1#{C:tarot} Tarot{}","dari toko","{C:inactive}(#2#)"]},"v_hone":{"name":"Hone","text":["Kartu {C:dark_edition}Foil{}, {C:dark_edition}Holographic{}, dan","{C:dark_edition}Polychrome{}","muncul {C:attention}#1#X{} lebih sering"]},"v_tarot_merchant":{"name":"Tarot Merchant","text":["Kartu {C:tarot}Tarot{} muncul","{C:attention}#1#X{} lebih sering","di toko"]},"v_reroll_surplus":{"name":"Reroll Surplus","text":["Biaya reroll","kurang dari {C:money}$#1#{}"]},"v_glow_up":{"text":["Kartu {C:dark_edition}Foil{}, {C:dark_edition}Holographic{}, dan","{C:dark_edition}Polychrome{}","muncul {C:attention}#1#X{} lebih sering"],"name":"Glow Up","unlock":["Miliki setidaknya {C:attention}#1#","kartu{C:attention}Joker{} dengan","edisi {C:dark_edition}Foil{}, {C:dark_edition}Holographic{}, dan","{C:dark_edition}Polychrome{}"]},"v_crystal_ball":{"name":"Crystal Ball","text":["{C:attention}+1{} slot habis pakai"]},"v_retcon":{"text":["Reroll Boss Blind","{C:attention}tanpa batas{} waktu,","{C:money}$#1#{} per roll"],"name":"Retcon","unlock":["Discover","{C:attention}#1#{} Blind"]},"v_reroll_glut":{"text":["Biaya reroll","kurang dari {C:money}$#1#{}"],"name":"Reroll Glut","unlock":["Reroll toko","total {C:attention}#1#{} kali","{C:inactive}(#2#)"]},"v_paint_brush":{"name":"Paint Brush","text":["{C:attention}+#1#{} ukuran hand"]},"v_grabber":{"name":"Grabber","text":["Secara permanen","memperoleh {C:blue}+#1#{} hand","per babak"]},"v_omen_globe":{"text":["Kartu {C:spectral}Spectral{} bisa juga","muncul dalam","{C:attention}Arcana Pack apa pun"],"name":"Omen Globe","unlock":["Pakai total {C:attention}#1#","kartu {C:tarot}Tarot{} dari","{C:tarot}Arcana Pack apa pun","{C:inactive}(#2#)"]},"v_wasteful":{"name":"Wasteful","text":["Secara permanen","mendapatkan {C:red}+#1#{} discard","setiap babak"]},"v_liquidation":{"text":["Semua kartu dan paket di","toko itu diskon {C:attention}#1#%{}"],"name":"Liquidation","unlock":["Tukarkan setidaknya","kartu {C:attention}#1#{C:voucher} Voucher{}","dalam satu giliran"]},"v_observatory":{"text":["kartu {C:planet}Planet{} di","area{C:attention}habis pakai{} Anda memberikan","{X:red,C:white} X#1# {} Mult untuk","{C:attention}poker hand tertentu"],"name":"Observatory","unlock":["Pakai total {C:attention}#1#","kartu {C:planet}Planet{} dari","{C:planet}Celestial Pack apa pun","{C:inactive}(#2#)"]},"v_planet_merchant":{"name":"Planet Merchant","text":["Kartu {C:planet}Planet{} muncul","{C:attention}#1#X{} lebih sering","di toko"]},"v_petroglyph":{"text":["{C:attention}-#1#{} Ante,","{C:red}-#1#{} discard","setiap babak"],"name":"Petroglyph","unlock":["Reach Ante","level {E:1,C:attention}#1#"]},"v_nacho_tong":{"text":["Secara permanen","memperoleh {C:blue}+#1#{} hand","per babak"],"name":"Nacho Tong","unlock":["Mainkan total","dari {C:attention}#1#{} kartu","{C:inactive}(#2#)"]},"v_palette":{"text":["{C:attention}+#1#{} ukuran hand"],"name":"Palette","unlock":["Kurangi ukuran hand","hingga {C:attention}#1#{} kartu"]},"v_seed_money":{"name":"Seed Money","text":["Naikkan batas","bunga yang diperoleh di","setiap babak menjadi {C:money}$#1#{}"]},"v_recyclomancy":{"text":["Secara permanen","mendapatkan {C:red}+#1#{} discard","setiap babak"],"name":"Recyclomancy","unlock":["Buang total","dari {C:attention}#1#{} kartu","{C:inactive}(#2#)"]},"v_blank":{"name":"Blank","text":["{C:inactive}Tidak apa-apa?"]},"v_overstock_norm":{"name":"Overstock","text":["{C:attention}+1{} slot kartu","tersedia di toko"]},"v_magic_trick":{"name":"Magic Trick","text":["{C:attention}Kartu permainan{} bisa","dibeli","dari {C:attention}toko"]},"v_illusion":{"text":["{C:attention}Kartu permainan{} di toko","mungkin memiliki sebuah {C:enhanced}Enhancement{},","{C:dark_edition}Edition{}, dan/atau sebuah {C:attention}Seal{}"],"name":"Illusion","unlock":["Beli total","{C:attention}#1#{} kartu permainan","dari toko","{C:inactive}(#2#)"]},"v_hieroglyph":{"name":"Hieroglyph","text":["{C:attention}-#1#{} Ante,","{C:blue}-#1#{} hand","setiap babak"]},"v_planet_tycoon":{"text":["Kartu {C:planet}Planet{} muncul","{C:attention}#1#X{} lebih sering","di toko"],"name":"Planet Tycoon","unlock":["Beli total","kartu{C:attention}#1#{C:planet} Planet{}","dari toko","{C:inactive}(#2#)"]},"v_directors_cut":{"name":"Director's Cut","text":["Reroll Boss Blind","{C:attention}1{} kali per Ante,","{C:money}$#1#{} per roll"]}},"Stake":{"stake_white":{"name":"White Stake","text":["Kesulitan Dasar"]},"stake_green":{"name":"Green Stake","text":["Memerlukan skala menang","yang lebih cepat untuk setiap {C:attention}Ante","{s:0.8}Memakai semua Stake sebelumnya"]},"stake_red":{"name":"Red Stake","text":["{C:attention}Small Blind{} memberikan","tanpa hadiah uang","{s:0.8}Memakai semua Stake sebelumnya"]},"stake_gold":{"name":"Gold Stake","text":["Shop bisa memiliki {C:attention}Rental{} Joker","{C:inactive,s:0.8}(Berbiaya {C:money,s:0.8}$3{C:inactive,s:0.8} per babak)","{s:0.8}Berlaku untuk semua Stake sebelumnya"]},"stake_black":{"name":"Black Stake","text":["Toko dapat memiliki {C:attention}Eternal{} Joker","{C:inactive,s:0.8}{Tidak bisa dijual atau dihancurkan}","{s:0.8}Memakai semua Stake sebelumnya"]},"stake_blue":{"name":"Blue Stake","text":["{C:red}-1{} Discard","{s:0.8}Memakai semua Stake sebelumnya"]},"stake_orange":{"name":"Orange Stake","text":["Shop bisa memiliki {C:attention}Perishable{} Joker","{C:inactive,s:0.8}(Terkena debuff setelah 5 Babak)","{s:0.8}Berlaku untuk semua Stake sebelumnya"]},"stake_purple":{"name":"Purple Stake","text":["Memerlukan skala menang","yang lebih cepat untuk setiap {C:attention}Ante","{s:0.8}Memakai semua Stake sebelumnya"]}},"Planet":{"c_ceres":{"name":"Ceres","text":["{S:0.8}({S:0.8,V:1}lvl.#1#{S:0.8}){} Menaikkan level","{C:attention}#2#","{C:mult}+#3#{} Mult dan","{C:chips}+#4#{} chip"]},"c_jupiter":{"name":"Jupiter","text":["{S:0.8}({S:0.8,V:1}lvl.#1#{S:0.8}){} Menaikkan level","{C:attention}#2#","{C:mult}+#3#{} Mult dan","{C:chips}+#4#{} chip"]},"c_eris":{"name":"Eris","text":["{S:0.8}({S:0.8,V:1}lvl.#1#{S:0.8}){} Menaikkan level","{C:attention}#2#","{C:mult}+#3#{} Mult dan","{C:chips}+#4#{} chip"]},"c_saturn":{"name":"Saturn","text":["{S:0.8}({S:0.8,V:1}lvl.#1#{S:0.8}){} Menaikkan level","{C:attention}#2#","{C:mult}+#3#{} Mult dan","{C:chips}+#4#{} chip"]},"c_uranus":{"name":"Uranus","text":["{S:0.8}({S:0.8,V:1}lvl.#1#{S:0.8}){} Menaikkan level","{C:attention}#2#","{C:mult}+#3#{} Mult dan","{C:chips}+#4#{} chip"]},"c_neptune":{"name":"Neptune","text":["{S:0.8}({S:0.8,V:1}lvl.#1#{S:0.8}){} Menaikkan level","{C:attention}#2#","{C:mult}+#3#{} Mult dan","{C:chips}+#4#{} chip"]},"c_mercury":{"name":"Mercury","text":["{S:0.8}({S:0.8,V:1}lvl.#1#{S:0.8}){} Menaikkan level","{C:attention}#2#","{C:mult}+#3#{} Mult dan","{C:chips}+#4#{} chip"]},"c_pluto":{"name":"Pluto","text":["{S:0.8}({S:0.8,V:1}lvl.#1#{S:0.8}){} Menaikkan level","{C:attention}#2#","{C:mult}+#3#{} Mult dan","{C:chips}+#4#{} chip"]},"c_planet_x":{"name":"Planet X","text":["{S:0.8}({S:0.8,V:1}lvl.#1#{S:0.8}){} Menaikkan level","{C:attention}#2#","{C:mult}+#3#{} Mult dan","{C:chips}+#4#{} chip"]},"c_earth":{"name":"Earth","text":["{S:0.8}({S:0.8,V:1}lvl.#1#{S:0.8}){} Menaikkan level","{C:attention}#2#","{C:mult}+#3#{} Mult dan","{C:chips}+#4#{} chip"]},"c_venus":{"name":"Venus","text":["{S:0.8}({S:0.8,V:1}lvl.#1#{S:0.8}){} Menaikkan level","{C:attention}#2#","{C:mult}+#3#{} Mult dan","{C:chips}+#4#{} chip"]},"c_mars":{"name":"Mars","text":["{S:0.8}({S:0.8,V:1}lvl.#1#{S:0.8}){} Menaikkan level","{C:attention}#2#","{C:mult}+#3#{} Mult dan","{C:chips}+#4#{} chip"]}},"Edition":{"e_negative_consumable":{"name":"Negatif","text":["{C:dark_edition}+#1#{} slot habis pakai"]},"e_negative":{"name":"Negatif","text":["{C:dark_edition}+#1#{} slot Joker"]},"e_base":{"name":"Base","text":["Tanpa efek tambahan"]},"e_foil":{"name":"Foil","text":["{C:chips}+#1#{} chip"]},"e_polychrome":{"name":"Polychrome","text":["{X:mult,C:white} X#1# {} Mult"]},"e_holo":{"name":"Holographic","text":["{C:mult}+#1#{} Mult"]}},"Spectral":{"c_talisman":{"name":"Talisman","text":["Tambahkan sebuah {C:attention}Gold Seal{}","ke {C:attention}1{} kartu","kartu di hand Anda"]},"c_aura":{"name":"Aura","text":["Tambahkan efek {C:dark_edition}Foil{}, {C:dark_edition}Holographic{},","atau {C:dark_edition}Polychrome{} ke","{C:attention}1{} kartu pilihan di hand"]},"c_wraith":{"name":"Wraith","text":["Memunculkan secara acak","{C:red}Rare{C:attention} Joker{},","membuat uang hingga {C:money}$0"]},"c_sigil":{"name":"Sigil","text":["Mengubah semua kartu","di hand menjadi sebuah","rupa {C:attention}secara acak"]},"c_ouija":{"name":"Ouija","text":["Mengubah semua kartu","di hand menjadi sebuah","peringkat {C:attention}secara acak","{C:red}-1{} ukuran hand"]},"c_ectoplasm":{"name":"Ectoplasm","text":["Menambah {C:dark_edition}Negatif{} ke","{C:attention}Joker secara acak,","{C:red}-1{} ukuran hand"]},"c_immolate":{"name":"Immolate","text":["Menghancurkan {C:attention}#1#{} kartu","kartu di hand,","dapatkan {C:money}$#2#"]},"c_ankh":{"name":"Ankh","text":["Buat sebuah salinan","acak {C:attention}Joker{}, hancurkan","seluruh Joker lainnya"]},"c_deja_vu":{"name":"Deja Vu","text":["Tambahkan sebuah {C:red}Red Seal{}","hingga {C:attention}1{} kartu","kartu di hand Anda"]},"c_hex":{"name":"Hex","text":["Tambahkan {C:dark_edition}Polychrome{} ke sebuah","acak {C:attention}Joker{}, hancurkan","seluruh Joker lainnya"]},"c_familiar":{"name":"Familiar","text":["Hancurkan {C:attention}1{} kartu","kartu di hand Anda, menambah","{C:attention}#1#{} secara acak {C:attention}Enhanced face","{C:attention}kartu{} ke hand Anda"]},"c_medium":{"name":"Medium","text":["Tambahkan sebuah {C:purple}Purple Seal{}","ke {C:attention}1{} kartu","kartu di hand Anda"]},"c_cryptid":{"name":"Cryptid","text":["Buat {C:attention}#1#{} salinan","{C:attention}1{} kartu pilihan","di hand Anda"]},"c_trance":{"name":"Trance","text":["Tambahkan sebuah {C:blue}Blue Seal{}","ke {C:attention}1{} kartu","kartu di hand Anda"]},"c_soul":{"name":"The Soul","text":["Membuat sebuah","{C:legendary,E:1}Legendary{} Joker","{C:inactive}(Harus memiliki tempat)"]},"c_black_hole":{"name":"Black Hole","text":["Upgrade setiap","{C:legendary,E:1}poker hand","sebanyak {C:attention}1{} level"]},"c_grim":{"name":"Grim","text":["Hancurkan {C:attention}1{} kartu","kartu di hand Anda,","menambah {C:attention}#1#{} secara acak {C:attention}As","{C:attention}As{} ke hand Anda"]},"c_incantation":{"name":"Incantation","text":["Hancurkan {C:attention}1{} kartu","kartu di hand Anda, menambah {C:attention}#1#","secara acak {C:attention}kartu bernomor","{C:attention}bernomor{} ke hand Anda"]}},"Back":{"b_black":{"name":"Black Deck","text":["{C:attention}+#1#{} slot Joker","","{C:blue}-#2#{} hand","setiap babak"]},"b_red":{"name":"Red Deck","text":["{C:red}+#1#{} discard","setiap babak"]},"b_checkered":{"name":"Checkered Deck","text":["Mulai giliran dengan","{C:attention}26{C:spades} Sekop{} dan","{C:attention}26{C:hearts} Hati{} di deck"]},"b_challenge":{"name":"Challenge Deck","text":[""]},"b_zodiac":{"name":"Zodiac Deck","text":["Mulai giliran dengan","{C:tarot,T:v_tarot_merchant}#1#{},","{C:planet,T:v_planet_merchant}#2#{},","dan {C:attention,T:v_overstock_norm}#3#"]},"b_blue":{"name":"Blue Deck","text":["{C:blue}+#1#{} hand","setiap babak"]},"b_yellow":{"name":"Yellow Deck","text":["Mulai dengan","ekstra {C:money}$#1#"]},"b_green":{"name":"Green Deck","text":["Di akhir setiap Babak:","{C:money}$#1#{s:0.85} per sisa {C:blue}Hand","{C:money}$#2#{s:0.85} per sisa {C:red}Discard","Tidak mendapat {C:attention}Keuntungan"]},"b_painted":{"name":"Painted Deck","text":["{C:attention}+#1#{} ukuran hand","{C:red}#2#{} slot Joker"]},"b_nebula":{"name":"Nebula Deck","text":["Mulai giliran dengan","{C:planet,T:v_telescope}#1#{} voucher","","{C:red}#2#{} slot habis pakai"]},"b_magic":{"name":"Magic Deck","text":["Mulai giliran dengan","{C:tarot,T:v_crystal_ball}#1#{} voucher","dan {C:attention}2{} salinan","dari {C:tarot,T:c_fool}#2#"]},"b_anaglyph":{"name":"Anaglyph Deck","text":["Setelah mengalahkan setiap","{C:attention}Boss Blind{}, memperoleh sebuah","{C:attention,T:tag_double}#1#"]},"b_ghost":{"name":"Ghost Deck","text":["Kartu {C:spectral}Spectral{} bisa juga","muncul di toko,","mulai dengan kartu {C:spectral,T:c_hex}Hex{}"]},"b_plasma":{"name":"Plasma Deck","text":["Saldo {C:blue}Chip{} dan","{C:red}Mult{} saat menghitung","skor untuk hand yang dimainkan","{C:red}X#1#{} ukuran Blind base"]},"b_erratic":{"name":"Erratic Deck","text":["Semua {C:attention}Peringkat{} dan","{C:attention}Rupa{} di deck","diacak"]},"b_abandoned":{"name":"Abandoned Deck","text":["Mulai giliran dengan","tidak ada {C:attention}Kartu Wajah","di deck Anda"]}}},"misc":{"quips":{"lq_6":["Oh tidak, Anda","juga menggertak?"],"lq_7":["Sepertinya kita","menjadi lawakan!"],"dq_1":["Astaga! Kuharap kau","punya trik-trik","rahasia untuk","tantangan final ini!"],"wq_1":["Anda berhasil!"],"wq_2":["Anda menghadapinya","dengan cukup baik!"],"lq_1":["Mungkin Go Fish","itu menambah","kecepatan kita..."],"wq_3":["Sepertinya Anda","tidak menggertak!"],"lq_10":["Gagal total!"],"lq_2":["Kita dilipat seperti","jas murahan!"],"wq_5":["Sepertinya aku telah","mengajarimu dengan baik!"],"lq_3":["Saatnya kita","menghindar","dan mencoba lagi!"],"wq_6":["Anda membuat","permainan duel!"],"lq_4":["Engkau tahu apa","kata mereka,","house selalu menang!"],"wq_7":["Untungnya","aku tak bertaruh","melawanmu!"],"lq_8":["Andai aku punya tangan,","aku pasti akan","menutup mataku!"],"lq_9":["Aku memang","bodoh, apa","alasanmu?"],"lq_5":["Sepertinya kita","tahu siapa","sebenarnya Joker itu!"],"wq_4":["Sayangnya semua","chip ini","virtual..."]},"suits_singular":{"Hearts":"Hati","Clubs":"Keriting","Spades":"Sekop","Diamonds":"Wajik"},"tutorial":{"s_6":["Sekarang belilah kartu","lainnya dari {C:attention}Toko"],"fh_4":["Beberapa kartu juga memberi Anda","sejumlah {C:blue}Chip{},","arahkan kursor ke atas untuk melihatnya!"],"s_7":["Kartu {C:tarot}Tarot{} ini merupakan suatu","{C:attention}habis pakai{}. Yang satu ini akan","meningkatkan permainan kartu","Anda! Pertahankanlah."],"fh_4_touch":["Beberapa kartu juga memberi Anda","sejumlah {C:blue}Chip{},","tekan dan tahan untuk melihatnya!"],"fh_5":["Sekarang pilih hingga","{C:attention}5{} kartu untuk dimainkan","dan tekan {C:blue}'Mainkan Hand'"],"s_9":["Jika Anda cukup banyak menyimpan,","Anda bisa membeli sebuah {C:attention}Voucher{}.","{C:attention}Voucher{} secara pasif","meng-upgrade giliran Anda!"],"fh_6":["Anda juga dapat {C:red}'Membuang'{} hingga","{C:attention}5{} kartu pilihan","untuk mencoba dan memperkuat","hand lagi. Cobalah!"],"sb_1":["Halo! Namaku","{C:attention}Jimbo{}, aku siap membantu","Anda mempelajari cara bermain!"],"fh_7":["Awas! Anda cuma punya","sejumlah terbatas {C:blue}Hand","dan {C:red}Discard{} per babak"],"sb_2":["Tujuan Anda adalah mendapatkan","{C:blue}Chip{} untuk mengalahkan","musuh {C:attention}Blind"],"fh_8":["Dapatkan {C:attention}300 Chip{} sebelum","Anda kehabisan {C:blue}Hand","untuk memenangi babak ini.","Semoga berhasil!"],"sb_3":["Di sini ada sebuah {C:blue}Small Blind{},","Anda hanya perlu mendapat","{C:attention}300 Chip{} untuk mengalahkannya."],"s_1":["Bagus sekali! Sekarang","Anda {E:1}melimpah{} dengan {C:money}Uang Tunai{},","Anda bisa membeli beberapa kartu","baru dari {C:attention}Toko"],"sb_4":["Pilih {C:blue}Small Blind","untuk memulai babak!"],"sh_1":["Saat Anda mendapatkan lebih banyak kartu,","jangan lupa kalau Anda bisa mengaturnya kembali.","{C:attention}Joker{} memicu secara","berurutan dari kiri ke kanan"],"s_10":["Stok {C:attention}Voucher{} diisi kembali","setelah Anda mengalahkan","{C:attention}Boss Blind{}."],"bb_1":["Memilih {C:attention}Big Blind","akan mendapat sejumlah uang tunai"],"s_11":["Dan periksalah","{C:booster}Booster Packs{} di","setiap toko. Paketnya","penuh pernak-pernik!"],"bb_2":["Atau memilih untuk {C:attention}melewatinya","agar mendapat sebuah {C:attention}Tag{}! Setiap","{C:attention}Tag{} memiliki efek unik"],"sh_3":["Pilih hingga {C:attention}2{} kartu","di hand Anda dan tekan","{C:attention}'GUNAKAN'{} di kartu {C:tarot}Tarot{}","untuk meningkatkannya!"],"bb_3":["Namun perhatikan","si {C:attention}Boss Blind{}. Ia","punya kemampuan yang akan","diperlukan untuk membuat rencana."],"s_2":["Cobalah membeli","Iblis ganteng ini"],"bb_4":["Jika Anda mengalahkannya,","{C:attention}Ante{} naik dan semua","{C:attention}Blind{} menjadi lebih sulit"],"s_2_touch":["Cobalah membeli","Iblis ganteng ini!","Geser dari toko","ke area {C:attention}'BELI'{}"],"bb_5":["Kalahkan {C:attention}Ante{} #1# agar menang.","Sekarang pilih jalur Anda!"],"s_3":["Ini merupakan salah satu {C:attention}#1#","{C:attention}Joker{} yang bisa ditambahkan ke","giliran Anda. Setiap {C:attention}Joker","membuat sesuatu yang berbeda"],"sh_3_touch":["Pilih hingga {C:attention}2{} kartu","di hand Anda dan geser","kartu Tarot {C:tarot}{} ke area {C:attention}'GUNAKAN'{}","untuk meningkatkannya!"],"fh_1":["Anda mendapat chip dengan","memainkan {C:attention}Poker hand"],"sh_2":["Dan memastikan bahwa Anda","{C:attention}MEMAKAI{} habis pakai Anda!"],"fh_5_touch":["Sekarang tekan hingga","{C:attention}5{} kartu untuk dimainkan","dan tekan {C:blue}'Mainkan Hand'"],"s_4":["Yang satu ini menambahkan {C:red}+4 Mult{} ke","setiap hand yang Anda mainkan!"],"s_12":["Marilah kita maju ke","{C:attention}babak berikutnya{}."],"fh_2":["Setiap {C:attention}Poker hand{} mendapatkan","sejumlah dasar {C:blue}Chip","diperbanyak oleh sejumlah {C:red}Mult"],"s_5":["Jadilah pemilih, Anda cuma dapat","membawa {C:attention}5 kartu{} Joker","pada saat bersamaan"],"fh_3":["Lihat {C:attention}Poker hand Anda","di area {C:attention}Info Giliran{},","bersama dengan info lainnya","tentang giliran Anda saat ini"],"s_8":["Sekarang pilihlah hingga","{C:attention}2 kartu{} habis pakai","pada suatu saat"]},"achievement_names":{"completionist_plus_plus":"Completionist++","extreme_couponer":"Pemilik Kupon Ekstrem","you_get_what_you_get":"Anda Mendapat Apa yang Didapat","flushed":"Flush","ante_up":"Ante Naik!","heads_up":"Duel","_100000k":"100.000K","high_stakes":"Taruhan Besar","_1000k":"1.000K","legendary":"Legendaris","_10k":"10K","low_stakes":"Taruhan Kecil","tiny_hands":"Hand Kecil","ante_upper":"Ante Naik Lagi!","speedrunner":"Speedrunner","astronomy":"Astronomi","shattered":"Shattered","big_hands":"Hand Besar","rule_breaker":"Rule Breaker","card_discarder":"Pembuang Kartu","rule_bender":"Rule Bender","card_player":"Pemain Kartu","royale":"Royale","cartomancy":"Ramalan Kartu","roi":"ROI","clairvoyance":"Kewaskitaan","retrograde":"Retrograde","completionist":"Completionist","nest_egg":"Nest Egg","completionist_plus":"Completionist+","mid_stakes":"Taruhan Sedang"},"labels":{"rental":"Rental","eternal":"Eternal","common":"Common","holographic":"Holographic","planet":"Planet","pinned_left":"Disematkan","rare":"Rare","uncommon":"Uncommon","negative":"Negatif","foil":"Foil","voucher":"Voucher","pluto_planet":"Dwarf Planet","locked":"Dikunci","red_seal":"Red Seal","legendary":"Legendary","blue_seal":"Blue Seal","perishable":"Perishable","polychrome":"Polychrome","gold_seal":"Gold Seal","tarot":"Tarot","purple_seal":"Purple Seal"},"challenge_names":{"c_knife_1":"Di Mata Pisau","c_luxury_1":"Pajak Barang Mewah","c_mad_world_1":"Dunia Gila","c_medusa_1":"Medusa","c_monolith_1":"Monolit","c_city_1":"Kota 15 Menit","c_cruelty_1":"Kekejaman","c_xray_1":"Penglihatan sinar-X","c_double_nothing_1":"Dobel atau Tidak","c_typecast_1":"Typecast","c_five_card_1":"Tarik Lima Kartu","c_rich_1":"Kaya makin Kaya","c_fragile_1":"Rapuh","c_omelette_1":"Dadar","c_golden_needle_1":"Jarum Emas","c_bram_poker_1":"Bram Poker","c_inflation_1":"Inflasi","c_blast_off_1":"Meluncur","c_jokerless_1":"Tanpa Joker","c_non_perishable_1":"Tidak Mudah Rusak"},"poker_hand_descriptions":{"Pair":["2 kartu yang memiliki peringkat yang sama. Keduanya mungkin","dimainkan dengan hingga 3 kartu tanpa kemenangan lainnya"],"Straight":["5 kartu berturut-turut {peringkat berurutan}"],"Flush Five":["5 kartu dengan peringkat dan rupa yang sama"],"Three of a Kind":["3 kartu dengan peringkat yang sama. Ketiganya mungkin","dimainkan dengan 2 kartu tanpa kemenangan lainnya"],"Straight Flush":["5 kartu berturut-turut {peringkat berurutan} dengan","semua kartu memiliki rupa yang sama"],"Two Pair":["2 pasang kartu dengan peringkat berbeda, mungkin","dimainkan dengan 1 kartu tanpa kemenangan lainnya"],"Royal Flush":["5 kartu berturut-turut {peringkat berurutan} dengan","semua kartu memiliki rupa yang sama"],"Four of a Kind":["4 kartu dengan peringkat yang sama. Keempatnya mungkin","dimainkan dengan 1 kartu tanpa kemenangan lainnya"],"Flush House":["Sebuah Three of a Kind dan sebuah Pair dengan","semua kartu memiliki rupa yang sama"],"Flush":["5 kartu yang memiliki rupa yang sama"],"High Card":["Jika hand yang dimainkan bukan salah satu hand","yang di atas, hanya kartu berperingkat tertinggi yang menang"],"Five of a Kind":["5 kartu dengan peringkat yang sama"],"Full House":["Sebuah Three of a Kind dan sebuah Pair dengan"]},"v_dictionary":{"ml_foil_desc":["Foil","+#1# Chip"],"a_remaining":"Tersisa #1#","ml_holo_desc":["Holographic","+#1# Mult"],"a_sold_tally":"Terjual #1#/#2#","a_xmult":" X#1# Mult","a_xmult_minus":"-X#1# Mult","remaining_discard_money":"Sisa Discard (masing-masing #1#$)","ante_x_voucher":"VOUCHER #1# ANTE","remaining_hand_money":"Sisa Hands (masing-masing #1#$)","challenges_completed":"Tantangan #1#/#2# Selesai","completed":"#1#/#2# Lengkap","deck_preview_wheel_plural":"Jumlahnya mungkin lebih rendah karena #1# kartu yang ditarik menghadap ke bawah","unlocked":"#1#/#2# Terbuka","ml_polychrome_desc":["Polychrome"," X#1# Mult"],"a_chips":"+#1#","ml_negative_desc":["Negatif","+#1# slot Joker"],"a_chips_minus":"-#1#","ml_negative_consumable_desc":["Negatif","+#1# Slot habis pakai"],"a_hands":"+#1# Hand","loyalty_inactive":"tersisa #1#","a_handsize":"+#1# ukuran hand","interest":"#1# keuntungan setiap $#2# (#3# maks)","deck_preview_wheel_singular":"Jumlahnya mungkin lebih rendah karena #1# kartu yang ditarik menghadap ke bawah","loyalty_active":"Aktif!","a_mult":"+#1# Mult","a_handsize_minus":"-#1# Ukuran Hand","a_mult_minus":"-#1# Mult"},"dictionary":{"k_view":"Tampilan","k_voucher":"Voucher","k_vouchers_cap":"VOUCHER","k_wins":"Menang","k_x_base":"X Base","ml_bloom_opt":["Mati","Nyala"],"ml_buy_and_use_target":["BELI","& PAKAI"],"ml_buy_target":["BELI"],"ml_card_stats":["Kartu","Stat"],"ml_controller_required":["Pengontrol permainan diperlukan untuk bermain.","Silakan sambungkan pengontrol untuk melanjutkan."],"ml_crash_report_info":["Laporan crash akan dikirim ke pengembang","agar kelak mengurangi masalah. Tidak ada","identifikasi atau info pribadi yang akan dikirim."],"b_FAQ":"Pertanyaan Umum","b_and_use":"& PAKAI","ml_demo_thanks_message":["Harap pertimbangkan wishlist","Balatro di Steam dan mendaftar agar","menerima buletin di playbalatro.com"],"b_back":"Kembali","b_blinds":"Blind","b_booster_packs":"Booster Pack","b_buy":"BELI","ml_edition_seal_enhancement_explanation":["Mungkin setiap kartu yang dimainkan punya satu","Enhancement, Edisi, dan Seal"],"b_cash_out":"Ambil Taruhan","b_challenges":"Tantangan","ml_gold_seal_desc":["Gold Seal","kembali ke hand","saat dimainkan"],"b_collection":"Koleksi","b_collection_cap":"KOLEKSI","b_continue":"Lanjutkan","ml_open_target":["BUKA"],"b_copy":"Salin","ml_paste_seed":["Tempel","Unggul"],"b_copy_seed":"Salin Unggul","ml_play_discard_pos_opt":["Buang/Putar","Putar/Buang"],"b_create_profile":"Buat Profil","ml_redeem_target":["TUKAR"],"ml_sell_target":["JUAL"],"b_customize_deck":"Sesuaikan deck","ml_shadow_opt":["Nyala","Mati"],"ml_smoothing_opt":["Mati","Nyala"],"ml_unlock_all_explanation":["PERINGATAN! Membuka Koleksi lengkap","akan menonaktifkan prestasi untuk profil ini!"],"b_decks":"Decks","ml_unlock_all_trophies":["PERINGATAN! Membuka Koleksi lengkap","akan menonaktifkan trofi untuk profil ini!"],"b_discard":"Buang","b_editions":"Edisi","ml_windowmode_opt":["Berjendela","Layar Penuh","Tanpa Batas"],"b_endless":"Mode Tanpa Henti","b_enhanced_cards":"Kartu Enhanced","ph_1_level":"+1 Tingkat","b_full_deck":"Deck Lengkap","ph_4_7_of_clubs":"empat 7 dari Keriting","ph_alert_debuff_confirm":"Tekan 'Mainkan' lagi untuk mengonfirmasi","k_mult":"Mult","ph_all_poker_hand":"Semua Poker Hand","ph_blind_reward":"Hadiah: ","ph_blind_score_at_least":"Menang Setidaknya","b_load_profile":"Muat Profil","b_main_menu":"Menu Utama","b_music":"Musik","b_new_challenge":"Mulai Tantangan Baru","b_new_run":"Giliran Baru","b_next":"Berikutnya","b_next_round_1":"Berikutnya","b_next_round_2":"Babak","ph_defeat_this_blind_1":"Kalahkan blind ini","b_open":"BUKA","ph_defeat_this_blind_2":"untuk menemukannya","b_options":"Opsi","b_options_cap":"OPSI","b_planet_cards":"Kartu Planet","b_play_cap":"MAINKAN","b_play_hand":"Mainkan Hand","b_playbalatro":"Kunjungi playbalatro.com","b_poker_hands":"Poker Hand","ph_mr_bones":"Diselamatkan oleh Mr. Bones","b_quit_cap":"KELUAR","b_redeem":"TUKAR","b_reduced_motion":"Mengurangi Gerakan","ph_most_played":"(poker hand yang paling banyak dimainkan)","b_remaining":"Sisa","ph_score_cards_played":"Kartu yang Dimainkan","b_reroll_boss":"Reroll Boss","ph_score_cards_purchased":"Kartu yang Dibeli","b_reset_profile":"Reset Profil","ph_score_furthest_ante":"Ante","b_restrictions":"Larangan","ph_score_hand":"Hand Terbaik","b_retry":"Coba lagi","b_rules":"Aturan","b_run_info_1":"Giliran","b_run_info_2":"Info","b_seals":"Seal","b_seed":"Unggul","b_select":"PILIH","b_sell":"JUAL","b_set_CRT":"CRT","b_set_CRT_bloom":"CRT Bloom","b_set_apply":"Terapkan","b_set_audio":"Audio","b_set_crash_reports":"Laporan Crash","b_set_game":"Game","b_set_game_vol":"Volume Game","ph_you_win_demo":"ANDA MENANG DEMO!","b_set_gamespeed":"Kecepatan Game","b_set_graphics":"Grafik","b_set_master_vol":"Volume Utama","b_set_monitor":"Monitor Tampilan","b_set_music_vol":"Volume Musik","b_set_pixel_smoothing":"Penghalusan Seni Piksel","b_set_play_discard_pos":"Putar/Buang Posisi Tombol","b_set_rumble":"Controller Rumble","b_set_screenshake":"Goyangan layar","b_set_shadows":"Bayangan","b_set_vibration":"Getar","b_set_video":"Video","b_set_windowmode":"Mode Jendela","b_settings":"Pengaturan","b_skip":"Lewati","b_skip_blind":"Lewati Blind","b_skip_reward":"Lewati Hadiah","b_sort_hand":"Sortir Hand","b_sounds":"Suara","b_spectral_cards":"Kartu Spectral","b_stake":"Stake","b_start_new_run":"Giliran Baru","b_stat_consumables":"Habis Pakai","b_stat_jokers":"Joker","b_stat_planets":"Planet","b_stat_spectrals":"Spectral","b_stat_tarots":"Tarot","b_stat_vouchers":"Voucher","b_stats":"Stat","b_tags":"Tag","b_tarot_cards":"Kartu Tarot","b_unlock_all":"Buka Semua","b_use":"PAKAI","b_vouchers":"Voucher","b_wishlist":"Wishlist di Steam","k_aces":"As","k_achievement":"Prestasi","k_achievements_disabled":"Prestasi Dinonaktifkan","k_active_ex":"Aktif!","k_again_ex":"Lagi!","k_all_hands":"Semua Hand","k_also_applied":"Juga berlaku","k_ante":"Ante","k_ante_cap":"ANTE","k_arcana_pack":"Arcana Pack","k_balanced":"Seimbang","k_banned_cards":"Kartu Terlarang","k_banned_tags":"Tag Terlarang","k_base_cap":"BASE","k_base_cards":"Base Card","k_best_hand":"Best Hand","k_booster":"Booster","k_buffoon_pack":"Buffoon Pack","k_cap_consumables":"HABIS PAKAI","k_card_stats":"Stat Kartu","k_celestial_pack":"Celestial Pack","k_challenge_mode":"Mode Tantangan","k_challenges":"Tantangan","k_choose":"Memilih","k_collection":"Koleksi","k_common":"Common","k_compatible":"kompatibel","k_copied_ex":"Disalin!","k_custom_rules":"Aturan Kustom","k_daily_run":"Giliran Harian","k_debuffed":"Di-debuff","k_deck":"Deck","k_deck_stake_wins":"Taruhan Deck Menang","k_defeated_by":"Dikalahkan Oleh","k_demo_version_ex":"Versi Demo!","k_disabled_ex":"Dinonaktifkan!","k_drank_ex":"Mabuk!","k_duplicated_ex":"Diduplikasi!","k_dwarf_planet":"Dwarf Planet","k_active":"aktif","ph_no_boss_active":"tak ada bos aktif","k_edition":"Edisi","k_effective":"Efektif","k_empty_caps":"KOSONG","k_enter_name":"Masukkan Nama","k_enter_seed":"Masukkan Unggulan","k_enter_text":"Masukkan Teks","k_eroded_ex":"Terkikis!","k_extinct_ex":"Punah!","k_face_cards":"Kartu Wajah","k_game_modifiers":"Pengubah Game","k_gold":"Gold","k_high_score_ex":"Menang Besar!","k_hud_discards":"Discard","k_hud_hands":"Hand","k_incompatible":"tidak kompatibel","k_joker":"Joker","k_joker_stickers":"Stiker Joker","k_jokers_cap":"JOKER","k_legendary":"Legendary","k_level_prefix":"lvl.","k_level_up_ex":"Level Naik!","k_locked":"Dikunci","k_lower_score":"menang","k_lvl":"lvl.","k_melted_ex":"Meleleh!","k_money":"Uang","ph_you_win":"ANDA MENANG!","ph_vouchers_redeemed":"Voucher yang ditukarkan pada giliran ini","ph_up_ante_3":"Refresh Blind","ph_up_ante_2":"Naikkan semua Blind","ph_up_ante_1":"Naikkan Ante","ph_unscored_hand":"Hand tidak akan menang","k_no_other_jokers":"Tak boleh Joker lagi!","ph_stat_voucher":"Berapa kali Voucher ini telah ditukarkan","k_no_reward":"Tidak ada Hadiah","ph_stat_joker":"Total babak yang diselesaikan dengan kartu ini","k_no_room_ex":"Tak Ada Tempat!","ph_stat_consumable":"Berapa kali kartu ini telah dipakai","k_no_space_ex":"Tak Ada Ruang!","ph_sneak_peek":"Intip Sekilas","k_none":"Tidak Ada","k_nope_ex":"Tidak!","ph_select_challenge":"Pilih Tantangan","k_not_allowed_ex":"Tidak Diperbolehkan!","ph_score_times_rerolled":"Reroll Waktu","k_not_discovered":"Belum Ditemukan","k_numbered_cards":"Kartu Bernomor","ph_score_poker_hand":"Hand yang Paling Sering Dimainkan","k_or":"atau","k_other":"Lainnya","k_page":"Halaman","ph_score_new_collection":"Penemuan Baru","k_planet":"Planet","k_planet_q":"Planet?","ph_score_furthest_round":"Babak","k_playing_as":"Bermain sebagai","ph_score_cards_discarded":"Kartu yang Dibuang","k_plus_joker":"+1 Joker","ph_score_at_least":"Menang Setidaknya","k_plus_planet":"+1 Planet","ph_no_vouchers":"Tidak ada voucher yang ditukarkan pada giliran ini","k_plus_spectral":"+1 Spectral","ph_improve_run":"Perbaiki giliran Anda!","k_plus_stone":"+1 Stone","ph_game_over":"GAME OVER","k_plus_tarot":"+1 Tarot","ph_display_stickers":"Menampilkan Stiker Taruhan selama Giliran","k_poker_hand":"poker hand","ph_demo_thanks_2":"DEMO BALATRO","k_profile":"Profil","ph_demo_thanks_1":"Terima kasih sudah memutar","k_progress":"Progres","ph_defeat_the_boss":"Kalahkan Boss Blind","k_rank":"Peringkat","ph_deck_preview_stones":"Stone","k_rare":"Rare","ph_deck_preview_effective":"Total efektif karena Joker, Blind, dan peningkatan kartu","k_redeemed_ex":"Ditukarkan!","ph_click_confirm":"Tekan lagi untuk mengonfirmasi","k_reroll":"Reroll","ph_choose_blind_2":"Anda berikutnya","k_reset":"Reset","ph_choose_blind_1":"Pilih Blind","k_reward":"Hadiah","ph_boss_disabled":"Boss Dinonaktifkan!","k_round":"Babak","k_safe_ex":"Aman!","b_deck":"Deck","k_saved_ex":"Disimpan!","$":"$","k_seed":"Unggul","k_seeded_run":"Giliran yang Diunggulkan","b_delete_profile":"Hapus Profil","k_skipped_cap":"DILEWATI","b_current_profile":"Profil Saat Ini","k_spectral":"Spectral","k_spectral_pack":"Spectral Pack","k_stake":"Stake","k_stake_level":"Level Stake","ml_eternal":["Eternal","Tidak bisa dijual","atau dihancurkan"],"k_standard_pack":"Standard Pack","k_suit":"Rupa","b_imagery":"Citra","k_swapped_ex":"Ditukar!","b_high_contrast_cards":"Kartu High Contrast","k_tarot":"Tarot","k_trophies_disabled":"Trofi Dinonaktifkan","b_how_to_play":"Cara bermain","k_trophy":"Trofi","k_eaten_ex":"Dimakan!","k_uncommon":"Uncommon","b_jokers":"Joker","k_undisovered":"Belum Ditemukan","k_unknown":"?????","ml_disabled_seed":["Semua Terbuka dan","Penemuan dinonaktifkan"],"k_unlocked_ex":"Terbuka!","ml_offline_message":["Perangkat ini offline.","Penyimpanan saat ini mungkin bukan versi terbaru."],"k_upgrade_ex":"Upgrade!","b_credits":"Kredit","k_val_up":"Nilai Naik!","ml_vsync_opt":["VSync Nyala","VSync Mati"]},"high_scores":{"hand":"Best Hand","most_money":"Most Money","win_streak":"Best Win Streak","boss_streak":"Most Bosses dalam sebuah Row","collection":"Koleksi","poker_hand":"Most Played Hand","furthest_ante":"Highest Ante","current_streak":"","furthest_round":"Highest Round"},"v_text":{"ch_c_no_interest":["Tidak mendapat {C:attention}Keuntungan{} di akhir babak"],"ch_c_no_reward":["Semua {C:attention}Blind{} tidak memberikan hadiah uang"],"ch_c_no_reward_specific":["{C:attention}#1# Blind{} tidak memberikan hadiah uang"],"ch_c_no_shop_jokers":["Joker tidak lagi muncul di {C:attention}toko"],"ch_c_none":["{C:inactive}Tidak ada"],"ch_c_set_eternal_ante":["Saat ante {C:attention}#1#{} bos dikalahkan, semua Joker menjadi {C:attention}eternal"],"ch_c_set_joker_slots_ante":["Saat ante {C:attention}#1#{} bos dikalahkan, setel slot Joker menjadi {C:attention}0"],"ch_c_all_eternal":["Semua Joker toko adalah {C:eternal}Eternal{}"],"ch_c_chips_dollar_cap":["{C:blue}Chip{} tidak dapat melebihi {C:money}$ saat ini"],"ch_m_none":["{C:inactive}Tidak ada"],"ch_c_daily":["{E:1,s:1.2,C:red}Tantangan Harian!"],"ch_m_joker_slots":["{C:attention}#1#{} Joker Slot"],"ch_c_debuff_played_cards":["Semua kartu yang {C:attention}Dimainkan{} terkena {C:attention}debuff{} setelah menang"],"ch_m_hands":["{C:blue}#1#{} hand per babak"],"ch_c_discard_cost":["Buang setiap harga {C:money}$#1#{}"],"ch_m_hand_size":["{C:attention}#1#{} ukuran hand"],"ch_c_flipped_cards":["{C:green}1 di #1#{} kartu ditarik menghadap ke bawah"],"ch_m_dollars":["Mulai dengan {C:money}$#1#"],"ch_c_inflation":["Naikkan harga secara permanen sebesar {C:money}$1{} di setiap pembelian"],"ch_m_discards":["{C:red}#1#{} discard per babak"],"ch_c_minus_hand_size_per_X_dollar":["Pegang {C:red}-1{} kartu di hand untuk setiap {C:money}$#1#{} yang Anda miliki"],"ch_m_consumable_slots":["{C:attention}#1#{} Slot Habis Pakai"],"ch_c_no_extra_hand_money":["Ekstra {C:blue}Hand{} tidak lagi mendapat uang"],"ch_c_set_seed":["1 upaya dengan set Seed: {C:inactive}{Hidden}"]},"collabs":{"Hearts":{"2":"Among Us","5":"Divinity Original Sin 2","1":"Bawaan","3":"The Binding of Isaac","6":"Critical Role","4":"Cult of the Lamb","7":"Bugsnax"},"Clubs":{"2":"Vampire Survivors","5":"Warframe","1":"Bawaan","3":"Slay the Spire","6":"Vault-Tec","4":"Potion Craft","7":"Dead by Daylight"},"Spades":{"2":"The Witcher","5":"Don’t Starve","1":"Bawaan","3":"Cyberpunk 2077","6":"Assassin's Creed","4":"Shovel Knight","7":"Slay the Princess"},"Diamonds":{"2":"DAVE THE DIVER","5":"1000xRESIST","1":"Bawaan","3":"Stardew Valley","6":"Civilization VII","4":"Enter the Gungeon","7":"Rust"}},"achievement_descriptions":{"completionist_plus_plus":"Dapatkan Stiker Gold di setiap Joker","extreme_couponer":"Temukan setiap Voucer","you_get_what_you_get":"Menangi giliran tanpa reroll toko","flushed":"Mainkan Flush dengan 5 Wild Card","ante_up":"Raih Ante 4","heads_up":"Menangi Giliran","_100000k":"Menangi 100.000.000 Chip dengan sekali hand","high_stakes":"Menangi giliran setidaknya kesulitan Gold Stake","_1000k":"Menangi 1.000.000 Chip dengan sekali hand","legendary":"Temukan Legendary Joker","_10k":"Menangi 10.000 Chip dengan sekali hand","low_stakes":"Menangi giliran setidaknya kesulitan Red Stake","tiny_hands":"Kurangi deck Anda hingga 20 kartu atau kurang","ante_upper":"Raih Ante 8","speedrunner":"Menangi giliran dalam 12 babak atau kurang","astronomy":"Temukan setiap kartu Planet","shattered":"Pecahkan 2 Glass Card dengan sekali hand","big_hands":"Miliki 80 kartu atau lebih di deck Anda","rule_breaker":"Selesaikan setiap giliran tantangan","card_discarder":"Buang setidaknya 2500 Kartu","rule_bender":"Selesaikan giliran tantangan apa pun","card_player":"Memainkan setidaknya 2500 Kartu","royale":"Mainkan Royal Flush","cartomancy":"Temukan setiap kartu Tarot","roi":"Beli 5 Voucer dengan Ante 4","clairvoyance":"Temukan setiap kartu Spectral","retrograde":"Dapatkan poker hand apa pun hingga level 10","completionist":"Temukan 100% dari koleksi Anda","nest_egg":"Miliki $400 atau lebih selama sekali giliran","completionist_plus":"Menangi dengan setiap deck di kesulitan Gold Stake","mid_stakes":"Menangi giliran setidaknya kesulitan Black Stake"},"poker_hands":{"Pair":"Pair","Straight":"Straight","Flush Five":"Flush Five","Three of a Kind":"Three of a Kind","Straight Flush":"Straight Flush","Two Pair":"Two Pair","Royal Flush":"Royal Flush","Four of a Kind":"Four of a Kind","Flush House":"Flush House","Flush":"Flush","High Card":"High Card","Five of a Kind":"Five of a Kind","Full House":"Full House"},"ranks":{"2":"2","King":"King","8":"8","3":"3","9":"9","4":"4","10":"10","5":"5","Jack":"Jack","6":"6","Ace":"As","Queen":"Queen","7":"7"},"suits_plural":{"Hearts":"Hati","Clubs":"Keriting","Spades":"Sekop","Diamonds":"Wajik"},"blind_states":{"Selected":"Pilihan","Skipped":"Dilewati","Upcoming":"Mendatang","Current":"Saat ini","Defeated":"Dikalahkan","Select":"Pilih"}}}